kotlin version: 2.0.20
error message: org.jetbrains.kotlin.backend.common.BackendException: Backend Internal error: Exception during IR lowering
File being compiled: D:/Documents/Freelos/SISEM-Android/app/src/main/java/com/skgtecnologia/sisem/ui/sections/BodySection.kt
The root cause java.lang.RuntimeException was thrown at: org.jetbrains.kotlin.backend.jvm.codegen.FunctionCodegen.generate(FunctionCodegen.kt:47)
	at org.jetbrains.kotlin.backend.common.CodegenUtil.reportBackendException(CodegenUtil.kt:253)
	at org.jetbrains.kotlin.backend.common.CodegenUtil.reportBackendException$default(CodegenUtil.kt:236)
	at org.jetbrains.kotlin.backend.common.phaser.PerformByIrFilePhase.invokeSequential(performByIrFile.kt:65)
	at org.jetbrains.kotlin.backend.common.phaser.PerformByIrFilePhase.invoke(performByIrFile.kt:52)
	at org.jetbrains.kotlin.backend.common.phaser.PerformByIrFilePhase.invoke(performByIrFile.kt:38)
	at org.jetbrains.kotlin.backend.common.phaser.NamedCompilerPhase.phaseBody(CompilerPhase.kt:166)
	at org.jetbrains.kotlin.backend.common.phaser.AbstractNamedCompilerPhase.invoke(CompilerPhase.kt:113)
	at org.jetbrains.kotlin.backend.common.phaser.CompositePhase.invoke(PhaseBuilders.kt:27)
	at org.jetbrains.kotlin.backend.common.phaser.CompositePhase.invoke(PhaseBuilders.kt:14)
	at org.jetbrains.kotlin.backend.common.phaser.NamedCompilerPhase.phaseBody(CompilerPhase.kt:166)
	at org.jetbrains.kotlin.backend.common.phaser.AbstractNamedCompilerPhase.invoke(CompilerPhase.kt:113)
	at org.jetbrains.kotlin.backend.common.phaser.CompilerPhaseKt.invokeToplevel(CompilerPhase.kt:62)
	at org.jetbrains.kotlin.backend.jvm.JvmIrCodegenFactory.invokeCodegen(JvmIrCodegenFactory.kt:371)
	at org.jetbrains.kotlin.codegen.CodegenFactory.generateModule(CodegenFactory.kt:47)
	at org.jetbrains.kotlin.backend.jvm.JvmIrCodegenFactory.generateModuleInFrontendIRMode(JvmIrCodegenFactory.kt:433)
	at org.jetbrains.kotlin.cli.jvm.compiler.pipeline.JvmCompilerPipelineKt.generateCodeFromIr(jvmCompilerPipeline.kt:246)
	at org.jetbrains.kotlin.cli.jvm.compiler.pipeline.JvmCompilerPipelineKt.compileModulesUsingFrontendIrAndLightTree(jvmCompilerPipeline.kt:142)
	at org.jetbrains.kotlin.cli.jvm.K2JVMCompiler.doExecute(K2JVMCompiler.kt:148)
	at org.jetbrains.kotlin.cli.jvm.K2JVMCompiler.doExecute(K2JVMCompiler.kt:43)
	at org.jetbrains.kotlin.cli.common.CLICompiler.execImpl(CLICompiler.kt:103)
	at org.jetbrains.kotlin.cli.common.CLICompiler.execImpl(CLICompiler.kt:49)
	at org.jetbrains.kotlin.cli.common.CLITool.exec(CLITool.kt:101)
	at org.jetbrains.kotlin.incremental.IncrementalJvmCompilerRunner.runCompiler(IncrementalJvmCompilerRunner.kt:464)
	at org.jetbrains.kotlin.incremental.IncrementalJvmCompilerRunner.runCompiler(IncrementalJvmCompilerRunner.kt:73)
	at org.jetbrains.kotlin.incremental.IncrementalCompilerRunner.doCompile(IncrementalCompilerRunner.kt:506)
	at org.jetbrains.kotlin.incremental.IncrementalCompilerRunner.compileImpl(IncrementalCompilerRunner.kt:423)
	at org.jetbrains.kotlin.incremental.IncrementalCompilerRunner.compileNonIncrementally(IncrementalCompilerRunner.kt:301)
	at org.jetbrains.kotlin.incremental.IncrementalCompilerRunner.compile(IncrementalCompilerRunner.kt:129)
	at org.jetbrains.kotlin.daemon.CompileServiceImplBase.execIncrementalCompiler(CompileServiceImpl.kt:675)
	at org.jetbrains.kotlin.daemon.CompileServiceImplBase.access$execIncrementalCompiler(CompileServiceImpl.kt:92)
	at org.jetbrains.kotlin.daemon.CompileServiceImpl.compile(CompileServiceImpl.kt:1660)
	at jdk.internal.reflect.GeneratedMethodAccessor94.invoke(Unknown Source)
	at java.base/jdk.internal.reflect.DelegatingMethodAccessorImpl.invoke(DelegatingMethodAccessorImpl.java:43)
	at java.base/java.lang.reflect.Method.invoke(Method.java:568)
	at java.rmi/sun.rmi.server.UnicastServerRef.dispatch(UnicastServerRef.java:360)
	at java.rmi/sun.rmi.transport.Transport$1.run(Transport.java:200)
	at java.rmi/sun.rmi.transport.Transport$1.run(Transport.java:197)
	at java.base/java.security.AccessController.doPrivileged(AccessController.java:712)
	at java.rmi/sun.rmi.transport.Transport.serviceCall(Transport.java:196)
	at java.rmi/sun.rmi.transport.tcp.TCPTransport.handleMessages(TCPTransport.java:587)
	at java.rmi/sun.rmi.transport.tcp.TCPTransport$ConnectionHandler.run0(TCPTransport.java:828)
	at java.rmi/sun.rmi.transport.tcp.TCPTransport$ConnectionHandler.lambda$run$0(TCPTransport.java:705)
	at java.base/java.security.AccessController.doPrivileged(AccessController.java:399)
	at java.rmi/sun.rmi.transport.tcp.TCPTransport$ConnectionHandler.run(TCPTransport.java:704)
	at java.base/java.util.concurrent.ThreadPoolExecutor.runWorker(ThreadPoolExecutor.java:1136)
	at java.base/java.util.concurrent.ThreadPoolExecutor$Worker.run(ThreadPoolExecutor.java:635)
	at java.base/java.lang.Thread.run(Thread.java:833)
Caused by: java.lang.RuntimeException: Exception while generating code for:
FUN name:HandleListScroll visibility:private modality:FINAL <> ($receiver:androidx.compose.foundation.lazy.LazyListState, body:kotlin.collections.List<com.valkiria.uicomponents.components.BodyRowModel>, onAction:kotlin.Function1<@[ParameterName(name = "actionInput")] com.valkiria.uicomponents.action.UiAction, kotlin.Unit>, $composer:androidx.compose.runtime.Composer?, $changed:kotlin.Int) returnType:kotlin.Unit
  annotations:
    Composable
  $receiver: VALUE_PARAMETER name:<this> type:androidx.compose.foundation.lazy.LazyListState
  VALUE_PARAMETER name:body index:0 type:kotlin.collections.List<com.valkiria.uicomponents.components.BodyRowModel>
  VALUE_PARAMETER name:onAction index:1 type:kotlin.Function1<@[ParameterName(name = "actionInput")] com.valkiria.uicomponents.action.UiAction, kotlin.Unit>
  VALUE_PARAMETER name:$composer index:2 type:androidx.compose.runtime.Composer? [assignable]
  VALUE_PARAMETER name:$changed index:3 type:kotlin.Int
  BLOCK_BODY
    SET_VAR '$composer: androidx.compose.runtime.Composer? [assignable] declared in com.skgtecnologia.sisem.ui.sections.BodySectionKt.HandleListScroll' type=kotlin.Unit origin=null
      CALL 'public abstract fun startRestartGroup (key: kotlin.Int): androidx.compose.runtime.Composer declared in androidx.compose.runtime.Composer' type=androidx.compose.runtime.Composer origin=null
        $this: GET_VAR '$composer: androidx.compose.runtime.Composer? [assignable] declared in com.skgtecnologia.sisem.ui.sections.BodySectionKt.HandleListScroll' type=androidx.compose.runtime.Composer? origin=null
        key: CONST Int type=kotlin.Int value=1590889900
    VAR name:$dirty type:kotlin.Int [val]
      GET_VAR '$changed: kotlin.Int declared in com.skgtecnologia.sisem.ui.sections.BodySectionKt.HandleListScroll' type=kotlin.Int origin=null
    WHEN type=kotlin.Unit origin=IF
      BRANCH
        if: CALL 'public final fun EQEQ (arg0: kotlin.Any?, arg1: kotlin.Any?): kotlin.Boolean declared in kotlin.internal.ir' type=kotlin.Boolean origin=null
          arg0: CALL 'public final fun and (other: kotlin.Int): kotlin.Int [infix] declared in kotlin.Int' type=kotlin.Int origin=null
            $this: GET_VAR '$changed: kotlin.Int declared in com.skgtecnologia.sisem.ui.sections.BodySectionKt.HandleListScroll' type=kotlin.Int origin=null
            other: CONST Int type=kotlin.Int value=6
          arg1: CONST Int type=kotlin.Int value=0
        then: SET_VAR 'val $dirty: kotlin.Int [val] declared in com.skgtecnologia.sisem.ui.sections.BodySectionKt.HandleListScroll' type=kotlin.Unit origin=null
          CALL 'public final fun or (other: kotlin.Int): kotlin.Int [infix] declared in kotlin.Int' type=kotlin.Int origin=null
            $this: GET_VAR 'val $dirty: kotlin.Int [val] declared in com.skgtecnologia.sisem.ui.sections.BodySectionKt.HandleListScroll' type=kotlin.Int origin=null
            other: WHEN type=kotlin.Int origin=IF
              BRANCH
                if: CALL 'public abstract fun changed (value: kotlin.Any?): kotlin.Boolean declared in androidx.compose.runtime.Composer' type=kotlin.Boolean origin=null
                  $this: GET_VAR '$composer: androidx.compose.runtime.Composer? [assignable] declared in com.skgtecnologia.sisem.ui.sections.BodySectionKt.HandleListScroll' type=androidx.compose.runtime.Composer? origin=null
                  value: GET_VAR '<this>: androidx.compose.foundation.lazy.LazyListState declared in com.skgtecnologia.sisem.ui.sections.BodySectionKt.HandleListScroll' type=androidx.compose.foundation.lazy.LazyListState origin=null
                then: CONST Int type=kotlin.Int value=4
              BRANCH
                if: CONST Boolean type=kotlin.Boolean value=true
                then: CONST Int type=kotlin.Int value=2
    WHEN type=kotlin.Unit origin=IF
      BRANCH
        if: CALL 'public final fun EQEQ (arg0: kotlin.Any?, arg1: kotlin.Any?): kotlin.Boolean declared in kotlin.internal.ir' type=kotlin.Boolean origin=null
          arg0: CALL 'public final fun and (other: kotlin.Int): kotlin.Int [infix] declared in kotlin.Int' type=kotlin.Int origin=null
            $this: GET_VAR '$changed: kotlin.Int declared in com.skgtecnologia.sisem.ui.sections.BodySectionKt.HandleListScroll' type=kotlin.Int origin=null
            other: CONST Int type=kotlin.Int value=48
          arg1: CONST Int type=kotlin.Int value=0
        then: SET_VAR 'val $dirty: kotlin.Int [val] declared in com.skgtecnologia.sisem.ui.sections.BodySectionKt.HandleListScroll' type=kotlin.Unit origin=null
          CALL 'public final fun or (other: kotlin.Int): kotlin.Int [infix] declared in kotlin.Int' type=kotlin.Int origin=null
            $this: GET_VAR 'val $dirty: kotlin.Int [val] declared in com.skgtecnologia.sisem.ui.sections.BodySectionKt.HandleListScroll' type=kotlin.Int origin=null
            other: WHEN type=kotlin.Int origin=IF
              BRANCH
                if: CALL 'public open fun changedInstance (value: kotlin.Any?): kotlin.Boolean declared in androidx.compose.runtime.Composer' type=kotlin.Boolean origin=null
                  $this: GET_VAR '$composer: androidx.compose.runtime.Composer? [assignable] declared in com.skgtecnologia.sisem.ui.sections.BodySectionKt.HandleListScroll' type=androidx.compose.runtime.Composer? origin=null
                  value: GET_VAR 'body: kotlin.collections.List<com.valkiria.uicomponents.components.BodyRowModel> declared in com.skgtecnologia.sisem.ui.sections.BodySectionKt.HandleListScroll' type=kotlin.collections.List<com.valkiria.uicomponents.components.BodyRowModel> origin=null
                then: CONST Int type=kotlin.Int value=32
              BRANCH
                if: CONST Boolean type=kotlin.Boolean value=true
                then: CONST Int type=kotlin.Int value=16
    WHEN type=kotlin.Unit origin=IF
      BRANCH
        if: CALL 'public final fun EQEQ (arg0: kotlin.Any?, arg1: kotlin.Any?): kotlin.Boolean declared in kotlin.internal.ir' type=kotlin.Boolean origin=null
          arg0: CALL 'public final fun and (other: kotlin.Int): kotlin.Int [infix] declared in kotlin.Int' type=kotlin.Int origin=null
            $this: GET_VAR '$changed: kotlin.Int declared in com.skgtecnologia.sisem.ui.sections.BodySectionKt.HandleListScroll' type=kotlin.Int origin=null
            other: CONST Int type=kotlin.Int value=384
          arg1: CONST Int type=kotlin.Int value=0
        then: SET_VAR 'val $dirty: kotlin.Int [val] declared in com.skgtecnologia.sisem.ui.sections.BodySectionKt.HandleListScroll' type=kotlin.Unit origin=null
          CALL 'public final fun or (other: kotlin.Int): kotlin.Int [infix] declared in kotlin.Int' type=kotlin.Int origin=null
            $this: GET_VAR 'val $dirty: kotlin.Int [val] declared in com.skgtecnologia.sisem.ui.sections.BodySectionKt.HandleListScroll' type=kotlin.Int origin=null
            other: WHEN type=kotlin.Int origin=IF
              BRANCH
                if: CALL 'public open fun changedInstance (value: kotlin.Any?): kotlin.Boolean declared in androidx.compose.runtime.Composer' type=kotlin.Boolean origin=null
                  $this: GET_VAR '$composer: androidx.compose.runtime.Composer? [assignable] declared in com.skgtecnologia.sisem.ui.sections.BodySectionKt.HandleListScroll' type=androidx.compose.runtime.Composer? origin=null
                  value: GET_VAR 'onAction: kotlin.Function1<@[ParameterName(name = "actionInput")] com.valkiria.uicomponents.action.UiAction, kotlin.Unit> declared in com.skgtecnologia.sisem.ui.sections.BodySectionKt.HandleListScroll' type=kotlin.Function1<@[ParameterName(name = "actionInput")] com.valkiria.uicomponents.action.UiAction, kotlin.Unit> origin=null
                then: CONST Int type=kotlin.Int value=256
              BRANCH
                if: CONST Boolean type=kotlin.Boolean value=true
                then: CONST Int type=kotlin.Int value=128
    WHEN type=kotlin.Unit origin=IF
      BRANCH
        if: CALL 'public final fun OROR (arg0: kotlin.Boolean, arg1: kotlin.Boolean): kotlin.Boolean declared in kotlin.internal.ir' type=kotlin.Boolean origin=null
          arg0: CALL 'public final fun not (): kotlin.Boolean [operator] declared in kotlin.Boolean' type=kotlin.Boolean origin=null
            $this: CALL 'public final fun EQEQ (arg0: kotlin.Any?, arg1: kotlin.Any?): kotlin.Boolean declared in kotlin.internal.ir' type=kotlin.Boolean origin=null
              arg0: CALL 'public final fun and (other: kotlin.Int): kotlin.Int [infix] declared in kotlin.Int' type=kotlin.Int origin=null
                $this: GET_VAR 'val $dirty: kotlin.Int [val] declared in com.skgtecnologia.sisem.ui.sections.BodySectionKt.HandleListScroll' type=kotlin.Int origin=null
                other: CONST Int type=kotlin.Int value=147
              arg1: CONST Int type=kotlin.Int value=146
          arg1: CALL 'public final fun not (): kotlin.Boolean [operator] declared in kotlin.Boolean' type=kotlin.Boolean origin=null
            $this: CALL 'public abstract fun <get-skipping> (): kotlin.Boolean declared in androidx.compose.runtime.Composer' type=kotlin.Boolean origin=null
              $this: GET_VAR '$composer: androidx.compose.runtime.Composer? [assignable] declared in com.skgtecnologia.sisem.ui.sections.BodySectionKt.HandleListScroll' type=androidx.compose.runtime.Composer? origin=null
        then: BLOCK type=kotlin.Unit origin=null
          WHEN type=kotlin.Unit origin=IF
            BRANCH
              if: CALL 'public final fun isTraceInProgress (): kotlin.Boolean declared in androidx.compose.runtime.ComposerKt' type=kotlin.Boolean origin=null
              then: CALL 'public final fun traceEventStart (key: kotlin.Int, dirty1: kotlin.Int, dirty2: kotlin.Int, info: kotlin.String): kotlin.Unit declared in androidx.compose.runtime.ComposerKt' type=kotlin.Unit origin=null
                key: CONST Int type=kotlin.Int value=1590889900
                dirty1: GET_VAR 'val $dirty: kotlin.Int [val] declared in com.skgtecnologia.sisem.ui.sections.BodySectionKt.HandleListScroll' type=kotlin.Int origin=null
                dirty2: CONST Int type=kotlin.Int value=-1
                info: CONST String type=kotlin.String value="com.skgtecnologia.sisem.ui.sections.HandleListScroll (BodySection.kt:204)"
          WHEN type=kotlin.Unit origin=IF
            BRANCH
              if: CALL 'public final fun none <T> (predicate: kotlin.Function1<T of kotlin.collections.CollectionsKt.none, kotlin.Boolean>): kotlin.Boolean [inline] declared in kotlin.collections.CollectionsKt' type=kotlin.Boolean origin=null
                <T>: com.valkiria.uicomponents.components.BodyRowModel
                $receiver: GET_VAR 'body: kotlin.collections.List<com.valkiria.uicomponents.components.BodyRowModel> declared in com.skgtecnologia.sisem.ui.sections.BodySectionKt.HandleListScroll' type=kotlin.collections.List<com.valkiria.uicomponents.components.BodyRowModel> origin=null
                predicate: BLOCK type=kotlin.Function1<com.valkiria.uicomponents.components.BodyRowModel, kotlin.Boolean> origin=LAMBDA
                  COMPOSITE type=kotlin.Unit origin=null
                  FUNCTION_REFERENCE 'private final fun HandleListScroll$lambda$8 (it: com.valkiria.uicomponents.components.BodyRowModel): kotlin.Boolean declared in com.skgtecnologia.sisem.ui.sections.BodySectionKt' type=kotlin.Function1<com.valkiria.uicomponents.components.BodyRowModel, kotlin.Boolean> origin=INLINE_LAMBDA reflectionTarget=null
              then: BLOCK type=kotlin.Unit origin=null
                BLOCK type=kotlin.Nothing origin=null
                  COMPOSITE type=kotlin.Unit origin=null
                    COMPOSITE type=kotlin.Unit origin=null
                      WHEN type=kotlin.Unit origin=IF
                        BRANCH
                          if: CALL 'public final fun isTraceInProgress (): kotlin.Boolean declared in androidx.compose.runtime.ComposerKt' type=kotlin.Boolean origin=null
                          then: CALL 'public final fun traceEventEnd (): kotlin.Unit declared in androidx.compose.runtime.ComposerKt' type=kotlin.Unit origin=null
                      BLOCK type=kotlin.Unit origin=null
                        BLOCK type=kotlin.Unit origin=FOLDED_SAFE_CALL
                          WHEN type=kotlin.Unit origin=FOLDED_SAFE_CALL
                            BRANCH
                              if: COMPOSITE type=kotlin.Boolean origin=null
                                VAR IR_TEMPORARY_VARIABLE name:tmp0_safe_receiver type:androidx.compose.runtime.ScopeUpdateScope? [val]
                                  CALL 'public abstract fun endRestartGroup (): androidx.compose.runtime.ScopeUpdateScope? declared in androidx.compose.runtime.Composer' type=androidx.compose.runtime.ScopeUpdateScope? origin=null
                                    $this: GET_VAR '$composer: androidx.compose.runtime.Composer? [assignable] declared in com.skgtecnologia.sisem.ui.sections.BodySectionKt.HandleListScroll' type=androidx.compose.runtime.Composer? origin=null
                                CALL 'public final fun not (): kotlin.Boolean [operator] declared in kotlin.Boolean' type=kotlin.Boolean origin=null
                                  $this: CALL 'public final fun EQEQ (arg0: kotlin.Any?, arg1: kotlin.Any?): kotlin.Boolean declared in kotlin.internal.ir' type=kotlin.Boolean origin=null
                                    arg0: GET_VAR 'val tmp0_safe_receiver: androidx.compose.runtime.ScopeUpdateScope? [val] declared in com.skgtecnologia.sisem.ui.sections.BodySectionKt.HandleListScroll' type=androidx.compose.runtime.ScopeUpdateScope? origin=null
                                    arg1: CONST Null type=kotlin.Nothing? value=null
                              then: CALL 'public abstract fun updateScope (block: kotlin.Function2<androidx.compose.runtime.Composer, kotlin.Int, kotlin.Unit>): kotlin.Unit declared in androidx.compose.runtime.ScopeUpdateScope' type=kotlin.Unit origin=null
                                $this: GET_VAR 'val tmp0_safe_receiver: androidx.compose.runtime.ScopeUpdateScope? [val] declared in com.skgtecnologia.sisem.ui.sections.BodySectionKt.HandleListScroll' type=androidx.compose.runtime.ScopeUpdateScope? origin=null
                                block: BLOCK type=kotlin.Function2<androidx.compose.runtime.Composer?, kotlin.Int, kotlin.Unit> origin=LAMBDA
                                  COMPOSITE type=kotlin.Unit origin=null
                                  CALL 'public final fun <jvm-indy> <T> (dynamicCall: T of kotlin.jvm.internal.<jvm-indy>, bootstrapMethodHandle: kotlin.Any, vararg bootstrapMethodArguments: kotlin.Any): T of kotlin.jvm.internal.<jvm-indy> declared in kotlin.jvm.internal' type=kotlin.Function2<androidx.compose.runtime.Composer?, kotlin.Int, kotlin.Unit> origin=null
                                    <T>: kotlin.Function2<androidx.compose.runtime.Composer?, kotlin.Int, kotlin.Unit>
                                    dynamicCall: CALL 'public final fun invoke (p0: androidx.compose.foundation.lazy.LazyListState, p1: kotlin.collections.List<com.valkiria.uicomponents.components.BodyRowModel>, p2: kotlin.Function1<@[ParameterName(name = "actionInput")] com.valkiria.uicomponents.action.UiAction, kotlin.Unit>, p3: kotlin.Int): kotlin.Function2<androidx.compose.runtime.Composer?, kotlin.Int, kotlin.Unit> declared in kotlin.jvm.internal.invokeDynamic' type=kotlin.Function2<androidx.compose.runtime.Composer?, kotlin.Int, kotlin.Unit> origin=null
                                      p0: GET_VAR '<this>: androidx.compose.foundation.lazy.LazyListState declared in com.skgtecnologia.sisem.ui.sections.BodySectionKt.HandleListScroll' type=androidx.compose.foundation.lazy.LazyListState origin=null
                                      p1: GET_VAR 'body: kotlin.collections.List<com.valkiria.uicomponents.components.BodyRowModel> declared in com.skgtecnologia.sisem.ui.sections.BodySectionKt.HandleListScroll' type=kotlin.collections.List<com.valkiria.uicomponents.components.BodyRowModel> origin=null
                                      p2: GET_VAR 'onAction: kotlin.Function1<@[ParameterName(name = "actionInput")] com.valkiria.uicomponents.action.UiAction, kotlin.Unit> declared in com.skgtecnologia.sisem.ui.sections.BodySectionKt.HandleListScroll' type=kotlin.Function1<@[ParameterName(name = "actionInput")] com.valkiria.uicomponents.action.UiAction, kotlin.Unit> origin=null
                                      p3: GET_VAR '$changed: kotlin.Int declared in com.skgtecnologia.sisem.ui.sections.BodySectionKt.HandleListScroll' type=kotlin.Int origin=null
                                    bootstrapMethodHandle: CALL 'public final fun <jvm-method-handle> (tag: kotlin.Int, owner: kotlin.String, name: kotlin.String, descriptor: kotlin.String, isInterface: kotlin.Boolean): kotlin.Any declared in kotlin.jvm.internal' type=kotlin.Any origin=null
                                      tag: CONST Int type=kotlin.Int value=6
                                      owner: CONST String type=kotlin.String value="java/lang/invoke/LambdaMetafactory"
                                      name: CONST String type=kotlin.String value="metafactory"
                                      descriptor: CONST String type=kotlin.String value="(Ljava/lang/invoke/MethodHandles$Lookup;Ljava/lang/String;Ljava/lang/invoke/MethodType;Ljava/lang/invoke/MethodType;Ljava/lang/invoke/MethodHandle;Ljava/lang/invoke/MethodType;)Ljava/lang/invoke/CallSite;"
                                      isInterface: CONST Boolean type=kotlin.Boolean value=false
                                    bootstrapMethodArguments: VARARG type=kotlin.Array<kotlin.Any> varargElementType=kotlin.Any
                                      CALL 'public final fun <jvm-original-method-type> (method: kotlin.Any): kotlin.Any declared in kotlin.jvm.internal' type=kotlin.Any origin=null
                                        method: RAW_FUNCTION_REFERENCE 'public abstract fun invoke (p1: P1 of kotlin.Function2, p2: P2 of kotlin.Function2): R of kotlin.Function2 [operator] declared in kotlin.Function2' type=kotlin.Any
                                      RAW_FUNCTION_REFERENCE 'private final fun HandleListScroll$lambda$9 ($this_HandleListScroll: androidx.compose.foundation.lazy.LazyListState, $body: kotlin.collections.List<com.valkiria.uicomponents.components.BodyRowModel>, $onAction: kotlin.Function1<@[ParameterName(name = "actionInput")] com.valkiria.uicomponents.action.UiAction, kotlin.Unit>, $$changed: kotlin.Int, $composer: androidx.compose.runtime.Composer?, $force: kotlin.Int): kotlin.Unit? declared in com.skgtecnologia.sisem.ui.sections.BodySectionKt' type=kotlin.Any
                                      CALL 'public final fun <jvm-original-method-type> (method: kotlin.Any): kotlin.Any declared in kotlin.jvm.internal' type=kotlin.Any origin=null
                                        method: RAW_FUNCTION_REFERENCE 'public abstract fun invoke (p1: androidx.compose.runtime.Composer?, p2: kotlin.Int?): kotlin.Unit? [fake_override,operator] declared in kotlin.jvm.internal.invokeDynamic.<fake>' type=kotlin.Any
                            BRANCH
                              if: CONST Boolean type=kotlin.Boolean value=true
                              then: CONST Null type=kotlin.Any? value=null
                  RETURN type=kotlin.Nothing from='private final fun HandleListScroll (body: kotlin.collections.List<com.valkiria.uicomponents.components.BodyRowModel>, onAction: kotlin.Function1<@[ParameterName(name = "actionInput")] com.valkiria.uicomponents.action.UiAction, kotlin.Unit>, $composer: androidx.compose.runtime.Composer?, $changed: kotlin.Int): kotlin.Unit declared in com.skgtecnologia.sisem.ui.sections.BodySectionKt'
                    GET_FIELD 'FIELD FIELD_FOR_OBJECT_INSTANCE name:INSTANCE type:kotlin.Unit visibility:public [final,static] declared in kotlin.Unit' type=kotlin.Unit origin=null
          VAR PROPERTY_DELEGATE name:headers$delegate type:androidx.compose.runtime.MutableState<kotlin.collections.List<kotlin.String>> [val]
            BLOCK type=androidx.compose.runtime.MutableState<kotlin.collections.List<kotlin.String>> origin=null
              CALL 'public final fun cache <T> (invalid: kotlin.Boolean, block: @[DisallowComposableCalls] kotlin.Function0<T of androidx.compose.runtime.ComposerKt.cache>): T of androidx.compose.runtime.ComposerKt.cache [inline] declared in androidx.compose.runtime.ComposerKt' type=androidx.compose.runtime.MutableState<kotlin.collections.List<kotlin.String>> origin=null
                <T>: androidx.compose.runtime.MutableState<kotlin.collections.List<kotlin.String>>
                $receiver: GET_VAR '$composer: androidx.compose.runtime.Composer? [assignable] declared in com.skgtecnologia.sisem.ui.sections.BodySectionKt.HandleListScroll' type=androidx.compose.runtime.Composer? origin=null
                invalid: CONST Boolean type=kotlin.Boolean value=false
                block: BLOCK type=kotlin.Function0<androidx.compose.runtime.MutableState<kotlin.collections.List<kotlin.String>>> origin=LAMBDA
                  COMPOSITE type=kotlin.Unit origin=null
                  FUNCTION_REFERENCE 'private final fun HandleListScroll$lambda$12 ($body: kotlin.collections.List<com.valkiria.uicomponents.components.BodyRowModel>): androidx.compose.runtime.MutableState<kotlin.collections.List<kotlin.String>> declared in com.skgtecnologia.sisem.ui.sections.BodySectionKt' type=kotlin.Function0<androidx.compose.runtime.MutableState<kotlin.collections.List<kotlin.String>>> origin=INLINE_LAMBDA reflectionTarget=null
                    $body: GET_VAR 'body: kotlin.collections.List<com.valkiria.uicomponents.components.BodyRowModel> declared in com.skgtecnologia.sisem.ui.sections.BodySectionKt.HandleListScroll' type=kotlin.collections.List<com.valkiria.uicomponents.components.BodyRowModel> origin=null
          VAR PROPERTY_DELEGATE name:firstVisibleSection$delegate type:androidx.compose.runtime.State<com.valkiria.uicomponents.components.header.HeaderUiModel?> [val]
            BLOCK type=androidx.compose.runtime.State<com.valkiria.uicomponents.components.header.HeaderUiModel?> origin=null
              CALL 'public final fun cache <T> (invalid: kotlin.Boolean, block: @[DisallowComposableCalls] kotlin.Function0<T of androidx.compose.runtime.ComposerKt.cache>): T of androidx.compose.runtime.ComposerKt.cache [inline] declared in androidx.compose.runtime.ComposerKt' type=androidx.compose.runtime.State<com.valkiria.uicomponents.components.header.HeaderUiModel?> origin=null
                <T>: androidx.compose.runtime.State<com.valkiria.uicomponents.components.header.HeaderUiModel?>
                $receiver: GET_VAR '$composer: androidx.compose.runtime.Composer? [assignable] declared in com.skgtecnologia.sisem.ui.sections.BodySectionKt.HandleListScroll' type=androidx.compose.runtime.Composer? origin=null
                invalid: CONST Boolean type=kotlin.Boolean value=false
                block: BLOCK type=kotlin.Function0<androidx.compose.runtime.State<com.valkiria.uicomponents.components.header.HeaderUiModel?>> origin=LAMBDA
                  COMPOSITE type=kotlin.Unit origin=null
                  FUNCTION_REFERENCE 'private final fun HandleListScroll$lambda$17 ($this_HandleListScroll: androidx.compose.foundation.lazy.LazyListState, $body: kotlin.collections.List<com.valkiria.uicomponents.components.BodyRowModel>, $headers$delegate: androidx.compose.runtime.MutableState<kotlin.collections.List<kotlin.String>>): androidx.compose.runtime.State<com.valkiria.uicomponents.components.header.HeaderUiModel?> declared in com.skgtecnologia.sisem.ui.sections.BodySectionKt' type=kotlin.Function0<androidx.compose.runtime.State<com.valkiria.uicomponents.components.header.HeaderUiModel?>> origin=INLINE_LAMBDA reflectionTarget=null
                    $this_HandleListScroll: GET_VAR '<this>: androidx.compose.foundation.lazy.LazyListState declared in com.skgtecnologia.sisem.ui.sections.BodySectionKt.HandleListScroll' type=androidx.compose.foundation.lazy.LazyListState origin=null
                    $body: GET_VAR 'body: kotlin.collections.List<com.valkiria.uicomponents.components.BodyRowModel> declared in com.skgtecnologia.sisem.ui.sections.BodySectionKt.HandleListScroll' type=kotlin.collections.List<com.valkiria.uicomponents.components.BodyRowModel> origin=null
                    $headers$delegate: GET_VAR 'val headers$delegate: androidx.compose.runtime.MutableState<kotlin.collections.List<kotlin.String>> [val] declared in com.skgtecnologia.sisem.ui.sections.BodySectionKt.HandleListScroll' type=androidx.compose.runtime.MutableState<kotlin.collections.List<kotlin.String>> origin=null
          COMPOSITE type=kotlin.Unit origin=null
            BLOCK type=kotlin.Unit? origin=FOLDED_SAFE_CALL
              WHEN type=kotlin.Unit? origin=FOLDED_SAFE_CALL
                BRANCH
                  if: CALL 'public final fun ANDAND (arg0: kotlin.Boolean, arg1: kotlin.Boolean): kotlin.Boolean declared in kotlin.internal.ir' type=kotlin.Boolean origin=null
                    arg0: CALL 'public final fun ANDAND (arg0: kotlin.Boolean, arg1: kotlin.Boolean): kotlin.Boolean declared in kotlin.internal.ir' type=kotlin.Boolean origin=null
                      arg0: COMPOSITE type=kotlin.Boolean origin=null
                        VAR IR_TEMPORARY_VARIABLE name:tmp0_safe_receiver type:com.valkiria.uicomponents.components.header.HeaderUiModel? [val]
                          CALL 'private final fun HandleListScroll$lambda$18 ($firstVisibleSection$delegate: androidx.compose.runtime.State<com.valkiria.uicomponents.components.header.HeaderUiModel?>): com.valkiria.uicomponents.components.header.HeaderUiModel? declared in com.skgtecnologia.sisem.ui.sections.BodySectionKt' type=com.valkiria.uicomponents.components.header.HeaderUiModel? origin=GET_LOCAL_PROPERTY
                            $firstVisibleSection$delegate: GET_VAR 'val firstVisibleSection$delegate: androidx.compose.runtime.State<com.valkiria.uicomponents.components.header.HeaderUiModel?> [val] declared in com.skgtecnologia.sisem.ui.sections.BodySectionKt.HandleListScroll' type=androidx.compose.runtime.State<com.valkiria.uicomponents.components.header.HeaderUiModel?> origin=null
                        CALL 'public final fun not (): kotlin.Boolean [operator] declared in kotlin.Boolean' type=kotlin.Boolean origin=null
                          $this: CALL 'public final fun EQEQ (arg0: kotlin.Any?, arg1: kotlin.Any?): kotlin.Boolean declared in kotlin.internal.ir' type=kotlin.Boolean origin=null
                            arg0: GET_VAR 'val tmp0_safe_receiver: com.valkiria.uicomponents.components.header.HeaderUiModel? [val] declared in com.skgtecnologia.sisem.ui.sections.BodySectionKt.HandleListScroll' type=com.valkiria.uicomponents.components.header.HeaderUiModel? origin=null
                            arg1: CONST Null type=kotlin.Nothing? value=null
                      arg1: COMPOSITE type=kotlin.Boolean origin=null
                        VAR IR_TEMPORARY_VARIABLE name:tmp1_safe_receiver type:com.valkiria.uicomponents.components.label.TextUiModel [val]
                          CALL 'public final fun <get-title> (): com.valkiria.uicomponents.components.label.TextUiModel declared in com.valkiria.uicomponents.components.header.HeaderUiModel' type=com.valkiria.uicomponents.components.label.TextUiModel origin=GET_PROPERTY
                            $this: GET_VAR 'val tmp0_safe_receiver: com.valkiria.uicomponents.components.header.HeaderUiModel? [val] declared in com.skgtecnologia.sisem.ui.sections.BodySectionKt.HandleListScroll' type=com.valkiria.uicomponents.components.header.HeaderUiModel? origin=null
                        CALL 'public final fun not (): kotlin.Boolean [operator] declared in kotlin.Boolean' type=kotlin.Boolean origin=null
                          $this: CALL 'public final fun EQEQ (arg0: kotlin.Any?, arg1: kotlin.Any?): kotlin.Boolean declared in kotlin.internal.ir' type=kotlin.Boolean origin=null
                            arg0: GET_VAR 'val tmp1_safe_receiver: com.valkiria.uicomponents.components.label.TextUiModel [val] declared in com.skgtecnologia.sisem.ui.sections.BodySectionKt.HandleListScroll' type=com.valkiria.uicomponents.components.label.TextUiModel origin=null
                            arg1: CONST Null type=kotlin.Nothing? value=null
                    arg1: COMPOSITE type=kotlin.Boolean origin=null
                      VAR IR_TEMPORARY_VARIABLE name:tmp2_safe_receiver type:kotlin.String [val]
                        CALL 'public final fun <get-text> (): kotlin.String declared in com.valkiria.uicomponents.components.label.TextUiModel' type=kotlin.String origin=GET_PROPERTY
                          $this: GET_VAR 'val tmp1_safe_receiver: com.valkiria.uicomponents.components.label.TextUiModel [val] declared in com.skgtecnologia.sisem.ui.sections.BodySectionKt.HandleListScroll' type=com.valkiria.uicomponents.components.label.TextUiModel? origin=null
                      CALL 'public final fun not (): kotlin.Boolean [operator] declared in kotlin.Boolean' type=kotlin.Boolean origin=null
                        $this: CALL 'public final fun EQEQ (arg0: kotlin.Any?, arg1: kotlin.Any?): kotlin.Boolean declared in kotlin.internal.ir' type=kotlin.Boolean origin=null
                          arg0: GET_VAR 'val tmp2_safe_receiver: kotlin.String [val] declared in com.skgtecnologia.sisem.ui.sections.BodySectionKt.HandleListScroll' type=kotlin.String origin=null
                          arg1: CONST Null type=kotlin.Nothing? value=null
                  then: CALL 'public final fun let <T, R> (block: kotlin.Function1<T of kotlin.StandardKt.let, R of kotlin.StandardKt.let>): R of kotlin.StandardKt.let [inline] declared in kotlin.StandardKt' type=kotlin.Unit origin=null
                    <T>: kotlin.String
                    <R>: kotlin.Unit
                    $receiver: GET_VAR 'val tmp2_safe_receiver: kotlin.String [val] declared in com.skgtecnologia.sisem.ui.sections.BodySectionKt.HandleListScroll' type=kotlin.String? origin=null
                    block: BLOCK type=kotlin.Function1<kotlin.String, kotlin.Unit> origin=LAMBDA
                      COMPOSITE type=kotlin.Unit origin=null
                      FUNCTION_REFERENCE 'private final fun HandleListScroll$lambda$19 ($onAction: kotlin.Function1<@[ParameterName(name = "actionInput")] com.valkiria.uicomponents.action.UiAction, kotlin.Unit>, it: kotlin.String): kotlin.Unit declared in com.skgtecnologia.sisem.ui.sections.BodySectionKt' type=kotlin.Function1<kotlin.String, kotlin.Unit> origin=INLINE_LAMBDA reflectionTarget=null
                        $onAction: GET_VAR 'onAction: kotlin.Function1<@[ParameterName(name = "actionInput")] com.valkiria.uicomponents.action.UiAction, kotlin.Unit> declared in com.skgtecnologia.sisem.ui.sections.BodySectionKt.HandleListScroll' type=kotlin.Function1<@[ParameterName(name = "actionInput")] com.valkiria.uicomponents.action.UiAction, kotlin.Unit> origin=null
                BRANCH
                  if: CONST Boolean type=kotlin.Boolean value=true
                  then: CONST Null type=kotlin.Nothing? value=null
          WHEN type=kotlin.Unit origin=IF
            BRANCH
              if: CALL 'public final fun isTraceInProgress (): kotlin.Boolean declared in androidx.compose.runtime.ComposerKt' type=kotlin.Boolean origin=null
              then: CALL 'public final fun traceEventEnd (): kotlin.Unit declared in androidx.compose.runtime.ComposerKt' type=kotlin.Unit origin=null
      BRANCH
        if: CONST Boolean type=kotlin.Boolean value=true
        then: CALL 'public abstract fun skipToGroupEnd (): kotlin.Unit declared in androidx.compose.runtime.Composer' type=kotlin.Unit origin=null
          $this: GET_VAR '$composer: androidx.compose.runtime.Composer? [assignable] declared in com.skgtecnologia.sisem.ui.sections.BodySectionKt.HandleListScroll' type=androidx.compose.runtime.Composer? origin=null
    BLOCK type=kotlin.Unit origin=null
      BLOCK type=kotlin.Unit origin=FOLDED_SAFE_CALL
        WHEN type=kotlin.Unit origin=FOLDED_SAFE_CALL
          BRANCH
            if: COMPOSITE type=kotlin.Boolean origin=null
              VAR IR_TEMPORARY_VARIABLE name:tmp1_safe_receiver type:androidx.compose.runtime.ScopeUpdateScope? [val]
                CALL 'public abstract fun endRestartGroup (): androidx.compose.runtime.ScopeUpdateScope? declared in androidx.compose.runtime.Composer' type=androidx.compose.runtime.ScopeUpdateScope? origin=null
                  $this: GET_VAR '$composer: androidx.compose.runtime.Composer? [assignable] declared in com.skgtecnologia.sisem.ui.sections.BodySectionKt.HandleListScroll' type=androidx.compose.runtime.Composer? origin=null
              CALL 'public final fun not (): kotlin.Boolean [operator] declared in kotlin.Boolean' type=kotlin.Boolean origin=null
                $this: CALL 'public final fun EQEQ (arg0: kotlin.Any?, arg1: kotlin.Any?): kotlin.Boolean declared in kotlin.internal.ir' type=kotlin.Boolean origin=null
                  arg0: GET_VAR 'val tmp1_safe_receiver: androidx.compose.runtime.ScopeUpdateScope? [val] declared in com.skgtecnologia.sisem.ui.sections.BodySectionKt.HandleListScroll' type=androidx.compose.runtime.ScopeUpdateScope? origin=null
                  arg1: CONST Null type=kotlin.Nothing? value=null
            then: CALL 'public abstract fun updateScope (block: kotlin.Function2<androidx.compose.runtime.Composer, kotlin.Int, kotlin.Unit>): kotlin.Unit declared in androidx.compose.runtime.ScopeUpdateScope' type=kotlin.Unit origin=null
              $this: GET_VAR 'val tmp1_safe_receiver: androidx.compose.runtime.ScopeUpdateScope? [val] declared in com.skgtecnologia.sisem.ui.sections.BodySectionKt.HandleListScroll' type=androidx.compose.runtime.ScopeUpdateScope? origin=null
              block: BLOCK type=kotlin.Function2<androidx.compose.runtime.Composer?, kotlin.Int, kotlin.Unit> origin=LAMBDA
                COMPOSITE type=kotlin.Unit origin=null
                CALL 'public final fun <jvm-indy> <T> (dynamicCall: T of kotlin.jvm.internal.<jvm-indy>, bootstrapMethodHandle: kotlin.Any, vararg bootstrapMethodArguments: kotlin.Any): T of kotlin.jvm.internal.<jvm-indy> declared in kotlin.jvm.internal' type=kotlin.Function2<androidx.compose.runtime.Composer?, kotlin.Int, kotlin.Unit> origin=null
                  <T>: kotlin.Function2<androidx.compose.runtime.Composer?, kotlin.Int, kotlin.Unit>
                  dynamicCall: CALL 'public final fun invoke (p0: androidx.compose.foundation.lazy.LazyListState, p1: kotlin.collections.List<com.valkiria.uicomponents.components.BodyRowModel>, p2: kotlin.Function1<@[ParameterName(name = "actionInput")] com.valkiria.uicomponents.action.UiAction, kotlin.Unit>, p3: kotlin.Int): kotlin.Function2<androidx.compose.runtime.Composer?, kotlin.Int, kotlin.Unit> declared in kotlin.jvm.internal.invokeDynamic' type=kotlin.Function2<androidx.compose.runtime.Composer?, kotlin.Int, kotlin.Unit> origin=null
                    p0: GET_VAR '<this>: androidx.compose.foundation.lazy.LazyListState declared in com.skgtecnologia.sisem.ui.sections.BodySectionKt.HandleListScroll' type=androidx.compose.foundation.lazy.LazyListState origin=null
                    p1: GET_VAR 'body: kotlin.collections.List<com.valkiria.uicomponents.components.BodyRowModel> declared in com.skgtecnologia.sisem.ui.sections.BodySectionKt.HandleListScroll' type=kotlin.collections.List<com.valkiria.uicomponents.components.BodyRowModel> origin=null
                    p2: GET_VAR 'onAction: kotlin.Function1<@[ParameterName(name = "actionInput")] com.valkiria.uicomponents.action.UiAction, kotlin.Unit> declared in com.skgtecnologia.sisem.ui.sections.BodySectionKt.HandleListScroll' type=kotlin.Function1<@[ParameterName(name = "actionInput")] com.valkiria.uicomponents.action.UiAction, kotlin.Unit> origin=null
                    p3: GET_VAR '$changed: kotlin.Int declared in com.skgtecnologia.sisem.ui.sections.BodySectionKt.HandleListScroll' type=kotlin.Int origin=null
                  bootstrapMethodHandle: CALL 'public final fun <jvm-method-handle> (tag: kotlin.Int, owner: kotlin.String, name: kotlin.String, descriptor: kotlin.String, isInterface: kotlin.Boolean): kotlin.Any declared in kotlin.jvm.internal' type=kotlin.Any origin=null
                    tag: CONST Int type=kotlin.Int value=6
                    owner: CONST String type=kotlin.String value="java/lang/invoke/LambdaMetafactory"
                    name: CONST String type=kotlin.String value="metafactory"
                    descriptor: CONST String type=kotlin.String value="(Ljava/lang/invoke/MethodHandles$Lookup;Ljava/lang/String;Ljava/lang/invoke/MethodType;Ljava/lang/invoke/MethodType;Ljava/lang/invoke/MethodHandle;Ljava/lang/invoke/MethodType;)Ljava/lang/invoke/CallSite;"
                    isInterface: CONST Boolean type=kotlin.Boolean value=false
                  bootstrapMethodArguments: VARARG type=kotlin.Array<kotlin.Any> varargElementType=kotlin.Any
                    CALL 'public final fun <jvm-original-method-type> (method: kotlin.Any): kotlin.Any declared in kotlin.jvm.internal' type=kotlin.Any origin=null
                      method: RAW_FUNCTION_REFERENCE 'public abstract fun invoke (p1: P1 of kotlin.Function2, p2: P2 of kotlin.Function2): R of kotlin.Function2 [operator] declared in kotlin.Function2' type=kotlin.Any
                    RAW_FUNCTION_REFERENCE 'private final fun HandleListScroll$lambda$20 ($this_HandleListScroll: androidx.compose.foundation.lazy.LazyListState, $body: kotlin.collections.List<com.valkiria.uicomponents.components.BodyRowModel>, $onAction: kotlin.Function1<@[ParameterName(name = "actionInput")] com.valkiria.uicomponents.action.UiAction, kotlin.Unit>, $$changed: kotlin.Int, $composer: androidx.compose.runtime.Composer?, $force: kotlin.Int): kotlin.Unit? declared in com.skgtecnologia.sisem.ui.sections.BodySectionKt' type=kotlin.Any
                    CALL 'public final fun <jvm-original-method-type> (method: kotlin.Any): kotlin.Any declared in kotlin.jvm.internal' type=kotlin.Any origin=null
                      method: RAW_FUNCTION_REFERENCE 'public abstract fun invoke (p1: androidx.compose.runtime.Composer?, p2: kotlin.Int?): kotlin.Unit? [fake_override,operator] declared in kotlin.jvm.internal.invokeDynamic.<fake>' type=kotlin.Any
          BRANCH
            if: CONST Boolean type=kotlin.Boolean value=true
            then: CONST Null type=kotlin.Any? value=null

	at org.jetbrains.kotlin.backend.jvm.codegen.FunctionCodegen.generate(FunctionCodegen.kt:47)
	at org.jetbrains.kotlin.backend.jvm.codegen.FunctionCodegen.generate$default(FunctionCodegen.kt:40)
	at org.jetbrains.kotlin.backend.jvm.codegen.ClassCodegen.generateMethodNode(ClassCodegen.kt:406)
	at org.jetbrains.kotlin.backend.jvm.codegen.ClassCodegen.generateMethod(ClassCodegen.kt:423)
	at org.jetbrains.kotlin.backend.jvm.codegen.ClassCodegen.generate(ClassCodegen.kt:168)
	at org.jetbrains.kotlin.backend.jvm.FileCodegen.lower(JvmPhases.kt:39)
	at org.jetbrains.kotlin.backend.common.phaser.PhaseFactoriesKt.createFilePhase$lambda$4(PhaseFactories.kt:71)
	at org.jetbrains.kotlin.backend.common.phaser.PhaseBuildersKt$createSimpleNamedCompilerPhase$1.phaseBody(PhaseBuilders.kt:69)
	at org.jetbrains.kotlin.backend.common.phaser.SimpleNamedCompilerPhase.phaseBody(CompilerPhase.kt:226)
	at org.jetbrains.kotlin.backend.common.phaser.AbstractNamedCompilerPhase.invoke(CompilerPhase.kt:113)
	at org.jetbrains.kotlin.backend.common.phaser.PerformByIrFilePhase.invokeSequential(performByIrFile.kt:62)
	... 44 more
Caused by: org.jetbrains.kotlin.codegen.CompilationException: Back-end (JVM) Internal error: Couldn't inline method call: CALL 'public final fun cache <T> (invalid: kotlin.Boolean, block: @[DisallowComposableCalls] kotlin.Function0<T of androidx.compose.runtime.ComposerKt.cache>): T of androidx.compose.runtime.ComposerKt.cache [inline] declared in androidx.compose.runtime.ComposerKt' type=androidx.compose.runtime.MutableState<kotlin.collections.List<kotlin.String>> origin=null
File is unknown
The root cause org.jetbrains.kotlin.codegen.inline.InlineException was thrown at: org.jetbrains.kotlin.codegen.inline.MethodInliner.wrapException(MethodInliner.kt:1123)
	at org.jetbrains.kotlin.codegen.inline.InlineCodegen.performInline(InlineCodegen.kt:60)
	at org.jetbrains.kotlin.backend.jvm.codegen.IrInlineCodegen.genInlineCall(IrInlineCodegen.kt:163)
	at org.jetbrains.kotlin.backend.jvm.codegen.IrInlineCallGenerator.genCall(IrInlineCallGenerator.kt:36)
	at org.jetbrains.kotlin.backend.jvm.codegen.ExpressionCodegen.visitCall(ExpressionCodegen.kt:653)
	at org.jetbrains.kotlin.backend.jvm.codegen.ExpressionCodegen.visitCall(ExpressionCodegen.kt:138)
	at org.jetbrains.kotlin.ir.expressions.IrCall.accept(IrCall.kt:24)
	at org.jetbrains.kotlin.backend.jvm.codegen.ExpressionCodegen.visitStatementContainer(ExpressionCodegen.kt:579)
	at org.jetbrains.kotlin.backend.jvm.codegen.ExpressionCodegen.visitContainerExpression(ExpressionCodegen.kt:593)
	at org.jetbrains.kotlin.backend.jvm.codegen.ExpressionCodegen.visitContainerExpression(ExpressionCodegen.kt:138)
	at org.jetbrains.kotlin.ir.visitors.IrElementVisitor$DefaultImpls.visitBlock(IrElementVisitor.kt:122)
	at org.jetbrains.kotlin.backend.jvm.codegen.ExpressionCodegen.visitBlock(ExpressionCodegen.kt:413)
	at org.jetbrains.kotlin.backend.jvm.codegen.ExpressionCodegen.visitBlock(ExpressionCodegen.kt:138)
	at org.jetbrains.kotlin.ir.expressions.IrBlock.accept(IrBlock.kt:18)
	at org.jetbrains.kotlin.backend.jvm.codegen.ExpressionCodegen.visitVariable(ExpressionCodegen.kt:790)
	at org.jetbrains.kotlin.backend.jvm.codegen.ExpressionCodegen.visitVariable(ExpressionCodegen.kt:138)
	at org.jetbrains.kotlin.ir.declarations.IrVariable.accept(IrVariable.kt:36)
	at org.jetbrains.kotlin.backend.jvm.codegen.ExpressionCodegen.visitStatementContainer(ExpressionCodegen.kt:579)
	at org.jetbrains.kotlin.backend.jvm.codegen.ExpressionCodegen.visitContainerExpression(ExpressionCodegen.kt:593)
	at org.jetbrains.kotlin.backend.jvm.codegen.ExpressionCodegen.visitContainerExpression(ExpressionCodegen.kt:138)
	at org.jetbrains.kotlin.ir.visitors.IrElementVisitor$DefaultImpls.visitBlock(IrElementVisitor.kt:122)
	at org.jetbrains.kotlin.backend.jvm.codegen.ExpressionCodegen.visitBlock(ExpressionCodegen.kt:413)
	at org.jetbrains.kotlin.backend.jvm.codegen.ExpressionCodegen.visitBlock(ExpressionCodegen.kt:138)
	at org.jetbrains.kotlin.ir.expressions.IrBlock.accept(IrBlock.kt:18)
	at org.jetbrains.kotlin.backend.jvm.codegen.ExpressionCodegen.visitWhen(ExpressionCodegen.kt:1101)
	at org.jetbrains.kotlin.backend.jvm.codegen.ExpressionCodegen.visitWhen(ExpressionCodegen.kt:138)
	at org.jetbrains.kotlin.ir.expressions.IrWhen.accept(IrWhen.kt:24)
	at org.jetbrains.kotlin.backend.jvm.codegen.ExpressionCodegen.visitStatementContainer(ExpressionCodegen.kt:579)
	at org.jetbrains.kotlin.backend.jvm.codegen.ExpressionCodegen.visitBlockBody(ExpressionCodegen.kt:584)
	at org.jetbrains.kotlin.backend.jvm.codegen.ExpressionCodegen.visitBlockBody(ExpressionCodegen.kt:138)
	at org.jetbrains.kotlin.ir.expressions.IrBlockBody.accept(IrBlockBody.kt:20)
	at org.jetbrains.kotlin.backend.jvm.codegen.ExpressionCodegen.generate(ExpressionCodegen.kt:240)
	at org.jetbrains.kotlin.backend.jvm.codegen.FunctionCodegen.doGenerate(FunctionCodegen.kt:123)
	at org.jetbrains.kotlin.backend.jvm.codegen.FunctionCodegen.generate(FunctionCodegen.kt:44)
	... 54 more
Caused by: org.jetbrains.kotlin.codegen.inline.InlineException: Lambda inlining com/skgtecnologia/sisem/ui/sections/BodySectionKt$HandleListScroll$headers$2: couldn't inline method call
Cause: HandleListScroll$lambda$12 (Ljava/util/List;)Landroidx/compose/runtime/MutableState;:
   L0
    ICONST_0
    ISTORE 1
   L1
    LINENUMBER 211 L1
    GETSTATIC com/skgtecnologia/sisem/ui/sections/BodySectionKt$HandleListScroll$headers$2.$$$$body : Ljava/util/List;
    CHECKCAST java/lang/Iterable
    ASTORE 3
   L2
    LINENUMBER 212 L2
    INVOKESTATIC kotlin/jvm/internal/InlineMarker.beforeInlineCall ()V
    NOP
   L3
    ICONST_0
    ISTORE 4
   L4
    LINENUMBER 808 L4
    ALOAD 3
    ASTORE 5
    NEW java/util/ArrayList
    DUP
    INVOKESPECIAL java/util/ArrayList.<init> ()V
    CHECKCAST java/util/Collection
    ASTORE 6
   L5
    ICONST_0
    ISTORE 7
   L6
    LINENUMBER 817 L6
    ALOAD 5
    INVOKEINTERFACE java/lang/Iterable.iterator ()Ljava/util/Iterator; (itf)
    ASTORE 8
   L7
    ALOAD 8
    INVOKEINTERFACE java/util/Iterator.hasNext ()Z (itf)
    IFEQ L8
    ALOAD 8
    INVOKEINTERFACE java/util/Iterator.next ()Ljava/lang/Object; (itf)
    ASTORE 9
   L9
    ALOAD 9
    INSTANCEOF com/valkiria/uicomponents/components/chip/FiltersUiModel
    IFEQ L7
    ALOAD 6
    ALOAD 9
    INVOKEINTERFACE java/util/Collection.add (Ljava/lang/Object;)Z (itf)
    POP
   L10
    GOTO L7
   L8
    LINENUMBER 818 L8
    ALOAD 6
   L11
    CHECKCAST java/util/List
   L12
    LINENUMBER 808 L12
    NOP
    GOTO L13
   L13
    INVOKESTATIC kotlin/jvm/internal/InlineMarker.afterInlineCall ()V
   L14
    LINENUMBER 213 L14
    INVOKESTATIC kotlin/collections/CollectionsKt.firstOrNull (Ljava/util/List;)Ljava/lang/Object;
    CHECKCAST com/valkiria/uicomponents/components/chip/FiltersUiModel
   L15
    LINENUMBER 211 L15
    ASTORE 2
   L16
    LINENUMBER 215 L16
    GETSTATIC com/skgtecnologia/sisem/ui/sections/BodySectionKt$HandleListScroll$headers$2.$$$$body : Ljava/util/List;
    CHECKCAST java/lang/Iterable
    ASTORE 4
   L17
    LINENUMBER 216 L17
    INVOKESTATIC kotlin/jvm/internal/InlineMarker.beforeInlineCall ()V
    NOP
   L18
    ICONST_0
    ISTORE 5
   L19
    LINENUMBER 819 L19
    ALOAD 4
    ASTORE 6
    NEW java/util/ArrayList
    DUP
    INVOKESPECIAL java/util/ArrayList.<init> ()V
    CHECKCAST java/util/Collection
    ASTORE 7
   L20
    ICONST_0
    ISTORE 8
   L21
    LINENUMBER 828 L21
    ALOAD 6
    INVOKEINTERFACE java/lang/Iterable.iterator ()Ljava/util/Iterator; (itf)
    ASTORE 9
   L22
    ALOAD 9
    INVOKEINTERFACE java/util/Iterator.hasNext ()Z (itf)
    IFEQ L23
    ALOAD 9
    INVOKEINTERFACE java/util/Iterator.next ()Ljava/lang/Object; (itf)
    ASTORE 10
   L24
    ALOAD 10
    INSTANCEOF com/valkiria/uicomponents/components/header/HeaderUiModel
    IFEQ L22
    ALOAD 7
    ALOAD 10
    INVOKEINTERFACE java/util/Collection.add (Ljava/lang/Object;)Z (itf)
    POP
   L25
    GOTO L22
   L23
    LINENUMBER 829 L23
    ALOAD 7
   L26
    CHECKCAST java/util/List
   L27
    LINENUMBER 819 L27
    NOP
    GOTO L28
   L28
    INVOKESTATIC kotlin/jvm/internal/InlineMarker.afterInlineCall ()V
    CHECKCAST java/lang/Iterable
    ASTORE 4
   L29
    LINENUMBER 217 L29
    INVOKESTATIC kotlin/jvm/internal/InlineMarker.beforeInlineCall ()V
    NOP
   L30
    ICONST_0
    ISTORE 5
   L31
    LINENUMBER 830 L31
    ALOAD 4
    ASTORE 6
    NEW java/util/ArrayList
    DUP
    INVOKESPECIAL java/util/ArrayList.<init> ()V
    CHECKCAST java/util/Collection
    ASTORE 7
   L32
    ICONST_0
    ISTORE 8
   L33
    LINENUMBER 831 L33
    ALOAD 6
    INVOKEINTERFACE java/lang/Iterable.iterator ()Ljava/util/Iterator; (itf)
    ASTORE 9
   L34
    ALOAD 9
    INVOKEINTERFACE java/util/Iterator.hasNext ()Z (itf)
    IFEQ L35
    ALOAD 9
    INVOKEINTERFACE java/util/Iterator.next ()Ljava/lang/Object; (itf)
    ASTORE 10
   L36
    ALOAD 10
    CHECKCAST com/valkiria/uicomponents/components/header/HeaderUiModel
    ASTORE 11
    INVOKESTATIC kotlin/jvm/internal/InlineMarker.beforeInlineCall ()V
   L37
    ICONST_0
    ISTORE 12
   L38
    LINENUMBER 217 L38
    ALOAD 2
    IFNULL L39
    ALOAD 2
    INVOKEVIRTUAL com/valkiria/uicomponents/components/chip/FiltersUiModel.getOptions ()Ljava/util/List;
    ASTORE 13
    ALOAD 13
    IFNULL L39
    ALOAD 13
    ALOAD 11
    INVOKEVIRTUAL com/valkiria/uicomponents/components/header/HeaderUiModel.getTitle ()Lcom/valkiria/uicomponents/components/label/TextUiModel;
    INVOKEVIRTUAL com/valkiria/uicomponents/components/label/TextUiModel.getText ()Ljava/lang/String;
    INVOKEINTERFACE java/util/List.contains (Ljava/lang/Object;)Z (itf)
    ICONST_1
    IF_ICMPNE L40
    ICONST_1
    GOTO L41
   L40
    ICONST_0
   L41
    GOTO L42
   L39
    ICONST_0
   L42
    NOP
    GOTO L43
   L43
    INVOKESTATIC java/lang/Boolean.valueOf (Z)Ljava/lang/Boolean;
    INVOKESTATIC kotlin/jvm/internal/InlineMarker.afterInlineCall ()V
   L44
    LINENUMBER 831 L44
    CHECKCAST java/lang/Boolean
    INVOKEVIRTUAL java/lang/Boolean.booleanValue ()Z
    IFEQ L34
    ALOAD 7
    ALOAD 10
    INVOKEINTERFACE java/util/Collection.add (Ljava/lang/Object;)Z (itf)
    POP
   L45
    GOTO L34
   L35
    LINENUMBER 832 L35
    ALOAD 7
   L46
    CHECKCAST java/util/List
   L47
    LINENUMBER 830 L47
    NOP
    GOTO L48
   L48
    INVOKESTATIC kotlin/jvm/internal/InlineMarker.afterInlineCall ()V
    CHECKCAST java/lang/Iterable
    ASTORE 4
   L49
    LINENUMBER 218 L49
    INVOKESTATIC kotlin/jvm/internal/InlineMarker.beforeInlineCall ()V
    NOP
   L50
    ICONST_0
    ISTORE 5
   L51
    LINENUMBER 833 L51
    ALOAD 4
    ASTORE 6
    NEW java/util/ArrayList
    DUP
    ALOAD 4
    BIPUSH 10
    INVOKESTATIC kotlin/collections/CollectionsKt.collectionSizeOrDefault (Ljava/lang/Iterable;I)I
    INVOKESPECIAL java/util/ArrayList.<init> (I)V
    CHECKCAST java/util/Collection
    ASTORE 7
   L52
    ICONST_0
    ISTORE 8
   L53
    LINENUMBER 834 L53
    ALOAD 6
    INVOKEINTERFACE java/lang/Iterable.iterator ()Ljava/util/Iterator; (itf)
    ASTORE 9
   L54
    ALOAD 9
    INVOKEINTERFACE java/util/Iterator.hasNext ()Z (itf)
    IFEQ L55
    ALOAD 9
    INVOKEINTERFACE java/util/Iterator.next ()Ljava/lang/Object; (itf)
    ASTORE 10
   L56
    LINENUMBER 835 L56
    ALOAD 7
    ALOAD 10
    CHECKCAST com/valkiria/uicomponents/components/header/HeaderUiModel
    ASTORE 11
    INVOKESTATIC kotlin/jvm/internal/InlineMarker.beforeInlineCall ()V
   L57
    ICONST_0
    ISTORE 12
   L58
    LINENUMBER 218 L58
    ALOAD 11
    INVOKEVIRTUAL com/valkiria/uicomponents/components/header/HeaderUiModel.getIdentifier ()Ljava/lang/String;
    NOP
    GOTO L59
   L59
    INVOKESTATIC kotlin/jvm/internal/InlineMarker.afterInlineCall ()V
   L60
    LINENUMBER 835 L60
    INVOKEINTERFACE java/util/Collection.add (Ljava/lang/Object;)Z (itf)
    POP
   L61
    GOTO L54
   L55
    LINENUMBER 836 L55
    ALOAD 7
   L62
    CHECKCAST java/util/List
   L63
    LINENUMBER 833 L63
    NOP
    GOTO L64
   L64
    INVOKESTATIC kotlin/jvm/internal/InlineMarker.afterInlineCall ()V
   L65
    LINENUMBER 218 L65
   L66
    LINENUMBER 215 L66
    ASTORE 3
   L67
    LINENUMBER 220 L67
    GETSTATIC timber/log/Timber.Forest : Ltimber/log/Timber$Forest;
    ALOAD 3
    INVOKEDYNAMIC makeConcatWithConstants(Ljava/util/List;)Ljava/lang/String; [
      // handle kind 0x6 : INVOKESTATIC
      java/lang/invoke/StringConcatFactory.makeConcatWithConstants(Ljava/lang/invoke/MethodHandles$Lookup;Ljava/lang/String;Ljava/lang/invoke/MethodType;Ljava/lang/String;[Ljava/lang/Object;)Ljava/lang/invoke/CallSite;
      // arguments:
      "headersFromBody: \u0001"
    ]
    ICONST_0
    ANEWARRAY java/lang/Object
    INVOKEVIRTUAL timber/log/Timber$Forest.d (Ljava/lang/String;[Ljava/lang/Object;)V
   L68
    LINENUMBER 221 L68
    ALOAD 3
    ACONST_NULL
    ICONST_2
    ACONST_NULL
    INVOKESTATIC androidx/compose/runtime/SnapshotStateKt.mutableStateOf$default (Ljava/lang/Object;Landroidx/compose/runtime/SnapshotMutationPolicy;ILjava/lang/Object;)Landroidx/compose/runtime/MutableState;
    ARETURN
   L69
    NOP
   L70
    LOCALVARIABLE element$iv$iv Ljava/lang/Object; L9 L10 9
    LOCALVARIABLE $i$f$filterIsInstanceTo I L6 L11 7
    LOCALVARIABLE $this$filterIsInstanceTo$iv$iv Ljava/lang/Iterable; L5 L11 5
    LOCALVARIABLE destination$iv$iv Ljava/util/Collection; L5 L11 6
    LOCALVARIABLE $i$f$filterIsInstance I L4 L13 4
    LOCALVARIABLE $this$filterIsInstance$iv Ljava/lang/Iterable; L3 L13 3
    LOCALVARIABLE element$iv$iv Ljava/lang/Object; L24 L25 10
    LOCALVARIABLE $i$f$filterIsInstanceTo I L21 L26 8
    LOCALVARIABLE $this$filterIsInstanceTo$iv$iv Ljava/lang/Iterable; L20 L26 6
    LOCALVARIABLE destination$iv$iv Ljava/util/Collection; L20 L26 7
    LOCALVARIABLE $i$f$filterIsInstance I L19 L28 5
    LOCALVARIABLE $this$filterIsInstance$iv Ljava/lang/Iterable; L18 L28 4
    LOCALVARIABLE $i$a$-filter-BodySectionKt$HandleListScroll$headers$2$headersFromBody$1 I L38 L43 12
    LOCALVARIABLE it Lcom/valkiria/uicomponents/components/header/HeaderUiModel; L37 L43 11
    LOCALVARIABLE element$iv$iv Ljava/lang/Object; L36 L45 10
    LOCALVARIABLE $i$f$filterTo I L33 L46 8
    LOCALVARIABLE $this$filterTo$iv$iv Ljava/lang/Iterable; L32 L46 6
    LOCALVARIABLE destination$iv$iv Ljava/util/Collection; L32 L46 7
    LOCALVARIABLE $i$f$filter I L31 L48 5
    LOCALVARIABLE $this$filter$iv Ljava/lang/Iterable; L30 L48 4
    LOCALVARIABLE $i$a$-map-BodySectionKt$HandleListScroll$headers$2$headersFromBody$2 I L58 L59 12
    LOCALVARIABLE it Lcom/valkiria/uicomponents/components/header/HeaderUiModel; L57 L59 11
    LOCALVARIABLE item$iv$iv Ljava/lang/Object; L56 L61 10
    LOCALVARIABLE $i$f$mapTo I L53 L62 8
    LOCALVARIABLE $this$mapTo$iv$iv Ljava/lang/Iterable; L52 L62 6
    LOCALVARIABLE destination$iv$iv Ljava/util/Collection; L52 L62 7
    LOCALVARIABLE $i$f$map I L51 L64 5
    LOCALVARIABLE $this$map$iv Ljava/lang/Iterable; L50 L64 4
    LOCALVARIABLE $i$a$-cache-BodySectionKt$HandleListScroll$headers$2 I L1 L70 1
    LOCALVARIABLE filtersComponent Lcom/valkiria/uicomponents/components/chip/FiltersUiModel; L16 L70 2
    LOCALVARIABLE headersFromBody Ljava/util/List; L67 L70 3
    LOCALVARIABLE $body Ljava/util/List; L0 L70 0
    MAXSTACK = 4
    MAXLOCALS = 15

	at org.jetbrains.kotlin.codegen.inline.MethodInliner.wrapException(MethodInliner.kt:1123)
	at org.jetbrains.kotlin.codegen.inline.MethodInliner.preprocessNodeBeforeInline(MethodInliner.kt:906)
	at org.jetbrains.kotlin.codegen.inline.MethodInliner.markPlacesForInlineAndRemoveInlinable(MethodInliner.kt:612)
	at org.jetbrains.kotlin.codegen.inline.MethodInliner.doInline(MethodInliner.kt:93)
	at org.jetbrains.kotlin.codegen.inline.MethodInliner.access$doInline(MethodInliner.kt:41)
	at org.jetbrains.kotlin.codegen.inline.MethodInliner$doInline$lambdaInliner$1.visitMethodInsn(MethodInliner.kt:353)
	at org.jetbrains.org.objectweb.asm.tree.MethodInsnNode.accept(MethodInsnNode.java:115)
	at org.jetbrains.org.objectweb.asm.tree.InsnList.accept(InsnList.java:144)
	at org.jetbrains.org.objectweb.asm.tree.MethodNode.accept(MethodNode.java:751)
	at org.jetbrains.kotlin.codegen.inline.MethodInliner.doInline(MethodInliner.kt:433)
	at org.jetbrains.kotlin.codegen.inline.MethodInliner.doInline(MethodInliner.kt:98)
	at org.jetbrains.kotlin.codegen.inline.MethodInliner.doInline(MethodInliner.kt:72)
	at org.jetbrains.kotlin.codegen.inline.InlineCodegen.inlineCall(InlineCodegen.kt:127)
	at org.jetbrains.kotlin.codegen.inline.InlineCodegen.performInline(InlineCodegen.kt:52)
	... 86 more
Caused by: java.lang.OutOfMemoryError: GC overhead limit exceeded


