kotlin version: 2.0.20
error message: org.jetbrains.kotlin.codegen.CompilationException: Back-end (JVM) Internal error: Couldn't transform method node:
BodySection (Ljava/util/List;Landroidx/compose/ui/Modifier;ZLkotlin/jvm/functions/Function1;Landroidx/compose/runtime/Composer;II)V:
  @Landroidx/compose/runtime/Composable;() // invisible
  @Landroidx/compose/runtime/ComposableTarget;(applier="androidx.compose.ui.UiComposable") // invisible
    // annotable parameter count: 7 (visible)
    // annotable parameter count: 7 (invisible)
    @Lorg/jetbrains/annotations/Nullable;() // invisible, parameter 0
    @Lorg/jetbrains/annotations/Nullable;() // invisible, parameter 1
    @Lorg/jetbrains/annotations/NotNull;() // invisible, parameter 3
    @Lorg/jetbrains/annotations/Nullable;() // invisible, parameter 4
   L0
    ALOAD 3
    LDC "onAction"
    INVOKESTATIC kotlin/jvm/internal/Intrinsics.checkNotNullParameter (Ljava/lang/Object;Ljava/lang/String;)V
   L1
    LINENUMBER 138 L1
    ALOAD 4
    LDC 2145635668
    INVOKEINTERFACE androidx/compose/runtime/Composer.startRestartGroup (I)Landroidx/compose/runtime/Composer; (itf)
    ASTORE 4
    ALOAD 4
    LDC "C(BodySection)P(!2,3)138@8259L23,139@8299L24:BodySection.kt#q4a1do"
    INVOKESTATIC androidx/compose/runtime/ComposerKt.sourceInformation (Landroidx/compose/runtime/Composer;Ljava/lang/String;)V
    ILOAD 5
    ISTORE 7
   L2
    ILOAD 6
    ICONST_1
    IAND
    IFEQ L3
    ILOAD 7
    BIPUSH 6
    IOR
    ISTORE 7
    GOTO L4
   L3
    ILOAD 5
    BIPUSH 6
    IAND
    IFNE L4
    ILOAD 7
    ALOAD 4
    ALOAD 0
    INVOKEINTERFACE androidx/compose/runtime/Composer.changedInstance (Ljava/lang/Object;)Z (itf)
    IFEQ L5
    ICONST_4
    GOTO L6
   L5
    ICONST_2
   L6
    IOR
    ISTORE 7
   L4
    ILOAD 6
    ICONST_2
    IAND
    IFEQ L7
    ILOAD 7
    BIPUSH 48
    IOR
    ISTORE 7
    GOTO L8
   L7
    ILOAD 5
    BIPUSH 48
    IAND
    IFNE L8
    ILOAD 7
    ALOAD 4
    ALOAD 1
    INVOKEINTERFACE androidx/compose/runtime/Composer.changed (Ljava/lang/Object;)Z (itf)
    IFEQ L9
    BIPUSH 32
    GOTO L10
   L9
    BIPUSH 16
   L10
    IOR
    ISTORE 7
   L8
    ILOAD 6
    ICONST_4
    IAND
    IFEQ L11
    ILOAD 7
    SIPUSH 384
    IOR
    ISTORE 7
    GOTO L12
   L11
    ILOAD 5
    SIPUSH 384
    IAND
    IFNE L12
    ILOAD 7
    ALOAD 4
    ILOAD 2
    INVOKEINTERFACE androidx/compose/runtime/Composer.changed (Z)Z (itf)
    IFEQ L13
    SIPUSH 256
    GOTO L14
   L13
    SIPUSH 128
   L14
    IOR
    ISTORE 7
   L12
    ILOAD 6
    BIPUSH 8
    IAND
    IFEQ L15
    ILOAD 7
    SIPUSH 3072
    IOR
    ISTORE 7
    GOTO L16
   L15
    ILOAD 5
    SIPUSH 3072
    IAND
    IFNE L16
    ILOAD 7
    ALOAD 4
    ALOAD 3
    INVOKEINTERFACE androidx/compose/runtime/Composer.changedInstance (Ljava/lang/Object;)Z (itf)
    IFEQ L17
    SIPUSH 2048
    GOTO L18
   L17
    SIPUSH 1024
   L18
    IOR
    ISTORE 7
   L16
    ILOAD 7
    SIPUSH 1171
    IAND
    SIPUSH 1170
    IF_ICMPNE L19
    ALOAD 4
    INVOKEINTERFACE androidx/compose/runtime/Composer.getSkipping ()Z (itf)
    IFNE L20
   L19
    ILOAD 6
    ICONST_2
    IAND
    IFEQ L21
   L22
    LINENUMBER 135 L22
    GETSTATIC androidx/compose/ui/Modifier.Companion : Landroidx/compose/ui/Modifier$Companion;
    CHECKCAST androidx/compose/ui/Modifier
    ASTORE 1
   L21
    ILOAD 6
    ICONST_4
    IAND
    IFEQ L23
   L24
    LINENUMBER 136 L24
    NOP
    ICONST_0
    ISTORE 2
   L23
    INVOKESTATIC androidx/compose/runtime/ComposerKt.isTraceInProgress ()Z
    IFEQ L25
    LDC 2145635668
    ILOAD 7
    ICONST_M1
    LDC "com.skgtecnologia.sisem.ui.sections.BodySection (BodySection.kt:137)"
   L26
    LINENUMBER 138 L26
    INVOKESTATIC androidx/compose/runtime/ComposerKt.traceEventStart (IIILjava/lang/String;)V
   L25
    ICONST_0
    ICONST_0
    ALOAD 4
    ICONST_0
    ICONST_3
   L27
    LINENUMBER 139 L27
    INVOKESTATIC androidx/compose/foundation/lazy/LazyListStateKt.rememberLazyListState (IILandroidx/compose/runtime/Composer;II)Landroidx/compose/foundation/lazy/LazyListState;
    ASTORE 8
   L28
    ICONST_0
    ISTORE 11
   L29
    LINENUMBER 140 L29
    NOP
   L30
    ICONST_0
    ISTORE 12
   L31
    ALOAD 4
    LDC 773894976
    LDC "CC(rememberCoroutineScope)482@20332L144:Effects.kt#9igjgp"
   L32
    LINENUMBER 808 L32
    INVOKESTATIC androidx/compose/runtime/ComposerKt.sourceInformationMarkerStart (Landroidx/compose/runtime/Composer;ILjava/lang/String;)V
   L33
    LINENUMBER 809 L33
    ALOAD 4
   L34
    LINENUMBER 811 L34
    ASTORE 13
   L35
    ALOAD 4
    LDC -954367824
    LDC "CC(remember):Effects.kt#9igjgp"
   L36
    LINENUMBER 812 L36
    INVOKESTATIC androidx/compose/runtime/ComposerKt.sourceInformationMarkerStart (Landroidx/compose/runtime/Composer;ILjava/lang/String;)V
    ALOAD 4
    ASTORE 14
    ICONST_0
    ISTORE 15
   L37
    ICONST_0
    ISTORE 16
   L38
    LINENUMBER 813 L38
    ALOAD 14
    INVOKEINTERFACE androidx/compose/runtime/Composer.rememberedValue ()Ljava/lang/Object; (itf)
    ASTORE 17
   L39
    ICONST_0
    ISTORE 18
   L40
    LINENUMBER 814 L40
    ALOAD 17
    GETSTATIC androidx/compose/runtime/Composer.Companion : Landroidx/compose/runtime/Composer$Companion;
    INVOKEVIRTUAL androidx/compose/runtime/Composer$Companion.getEmpty ()Ljava/lang/Object;
    IF_ACMPNE L41
   L42
    LINENUMBER 815 L42
    ICONST_0
    ISTORE 19
   L43
    LINENUMBER 816 L43
    NEW androidx/compose/runtime/CompositionScopedCoroutineScopeCanceller
    DUP
   L44
    LINENUMBER 817 L44
    NOP
    INVOKESTATIC kotlin/jvm/internal/InlineMarker.beforeInlineCall ()V
    ICONST_0
    ISTORE 20
   L45
    NOP
   L46
    LINENUMBER 818 L46
    GETSTATIC kotlin/coroutines/EmptyCoroutineContext.INSTANCE : Lkotlin/coroutines/EmptyCoroutineContext;
    GOTO L47
   L47
    NOP
    GOTO L48
   L48
    INVOKESTATIC kotlin/jvm/internal/InlineMarker.afterInlineCall ()V
   L49
    LINENUMBER 817 L49
    CHECKCAST kotlin/coroutines/CoroutineContext
    ALOAD 13
    INVOKESTATIC androidx/compose/runtime/EffectsKt.createCompositionCoroutineScope (Lkotlin/coroutines/CoroutineContext;Landroidx/compose/runtime/Composer;)Lkotlinx/coroutines/CoroutineScope;
   L50
    LINENUMBER 816 L50
    INVOKESPECIAL androidx/compose/runtime/CompositionScopedCoroutineScopeCanceller.<init> (Lkotlinx/coroutines/CoroutineScope;)V
   L51
    LINENUMBER 815 L51
    ASTORE 20
   L52
    LINENUMBER 819 L52
    ALOAD 14
    ALOAD 20
    INVOKEINTERFACE androidx/compose/runtime/Composer.updateRememberedValue (Ljava/lang/Object;)V (itf)
   L53
    LINENUMBER 820 L53
    ALOAD 20
   L54
    GOTO L55
   L41
    LINENUMBER 821 L41
    ALOAD 17
   L55
    LINENUMBER 814 L55
    NOP
   L56
    LINENUMBER 813 L56
    NOP
   L57
    LINENUMBER 813 L57
    NOP
   L58
    LINENUMBER 812 L58
    CHECKCAST androidx/compose/runtime/CompositionScopedCoroutineScopeCanceller
    ASTORE 21
    ALOAD 4
    INVOKESTATIC androidx/compose/runtime/ComposerKt.sourceInformationMarkerEnd (Landroidx/compose/runtime/Composer;)V
    ALOAD 21
    ASTORE 22
   L59
    LINENUMBER 822 L59
    ALOAD 22
    INVOKEVIRTUAL androidx/compose/runtime/CompositionScopedCoroutineScopeCanceller.getCoroutineScope ()Lkotlinx/coroutines/CoroutineScope;
    ASTORE 21
    ALOAD 4
   L60
    LINENUMBER 808 L60
    INVOKESTATIC androidx/compose/runtime/ComposerKt.sourceInformationMarkerEnd (Landroidx/compose/runtime/Composer;)V
    ALOAD 21
   L61
    LINENUMBER 822 L61
    NOP
    GOTO L62
   L62
    LINENUMBER 140 L62
    ASTORE 9
   L63
    LINENUMBER 142 L63
    ALOAD 0
    IFNULL L64
    NOP
   L65
    ALOAD 0
    CHECKCAST java/util/Collection
    INVOKEINTERFACE java/util/Collection.isEmpty ()Z (itf)
    IFNE L66
    ICONST_1
    GOTO L67
   L66
    ICONST_0
   L67
    NOP
    GOTO L68
   L68
    LINENUMBER 142 L68
    NOP
    ICONST_1
    IF_ICMPNE L69
    ICONST_1
    GOTO L70
   L69
    ICONST_0
   L70
    GOTO L71
   L64
    NOP
    NOP
    ICONST_0
   L71
    IFEQ L72
    ALOAD 4
    LDC -2121119141
    INVOKEINTERFACE androidx/compose/runtime/Composer.startReplaceGroup (I)V (itf)
    ALOAD 4
    LDC "142@8371L2118"
    INVOKESTATIC androidx/compose/runtime/ComposerKt.sourceInformation (Landroidx/compose/runtime/Composer;Ljava/lang/String;)V
   L73
    LINENUMBER 143 L73
    ALOAD 1
    FCONST_0
    ICONST_1
    ACONST_NULL
    INVOKESTATIC androidx/compose/foundation/layout/SizeKt.fillMaxSize$default (Landroidx/compose/ui/Modifier;FILjava/lang/Object;)Landroidx/compose/ui/Modifier;
    ASTORE 10
    ICONST_0
    ISTORE 13
    NOP
   L74
    ICONST_0
    ISTORE 14
   L75
    ALOAD 4
    LDC 733328855
    LDC "CC(Box)P(2,1,3)72@3384L130:Box.kt#2w3rfo"
   L76
    LINENUMBER 823 L76
    INVOKESTATIC androidx/compose/runtime/ComposerKt.sourceInformationMarkerStart (Landroidx/compose/runtime/Composer;ILjava/lang/String;)V
   L77
    LINENUMBER 824 L77
    GETSTATIC androidx/compose/ui/Alignment.Companion : Landroidx/compose/ui/Alignment$Companion;
    INVOKEVIRTUAL androidx/compose/ui/Alignment$Companion.getTopStart ()Landroidx/compose/ui/Alignment;
    ASTORE 11
   L78
    LINENUMBER 825 L78
    ICONST_0
    ISTORE 12
   L79
    LINENUMBER 828 L79
    ALOAD 11
    ILOAD 12
    INVOKESTATIC androidx/compose/foundation/layout/BoxKt.maybeCachedBoxMeasurePolicy (Landroidx/compose/ui/Alignment;Z)Landroidx/compose/ui/layout/MeasurePolicy;
    ASTORE 15
   L80
    BIPUSH 112
    ILOAD 13
    ICONST_3
    ISHL
    IAND
    ISTORE 16
   L81
    LINENUMBER 829 L81
    NOP
   L82
    ICONST_0
    ISTORE 17
   L83
    ALOAD 4
    LDC -1323940314
    LDC "CC(Layout)P(!1,2)79@3208L23,82@3359L411:Layout.kt#80mrfh"
   L84
    LINENUMBER 830 L84
    INVOKESTATIC androidx/compose/runtime/ComposerKt.sourceInformationMarkerStart (Landroidx/compose/runtime/Composer;ILjava/lang/String;)V
    ALOAD 4
    ICONST_0
   L85
    LINENUMBER 831 L85
    INVOKESTATIC androidx/compose/runtime/ComposablesKt.getCurrentCompositeKeyHash (Landroidx/compose/runtime/Composer;I)I
    ISTORE 18
   L86
    ALOAD 4
   L87
    LINENUMBER 832 L87
    INVOKEINTERFACE androidx/compose/runtime/Composer.getCurrentCompositionLocalMap ()Landroidx/compose/runtime/CompositionLocalMap; (itf)
    ASTORE 19
   L88
    ALOAD 4
   L89
    LINENUMBER 833 L89
    ALOAD 10
    INVOKESTATIC androidx/compose/ui/ComposedModifierKt.materializeModifier (Landroidx/compose/runtime/Composer;Landroidx/compose/ui/Modifier;)Landroidx/compose/ui/Modifier;
    ASTORE 20
   L90
    LINENUMBER 835 L90
    GETSTATIC androidx/compose/ui/node/ComposeUiNode.Companion : Landroidx/compose/ui/node/ComposeUiNode$Companion;
    INVOKEVIRTUAL androidx/compose/ui/node/ComposeUiNode$Companion.getConstructor ()Lkotlin/jvm/functions/Function0;
    ASTORE 21
    BIPUSH 6
    SIPUSH 896
    ILOAD 16
    BIPUSH 6
    ISHL
    IAND
    IOR
    ISTORE 22
   L91
    LINENUMBER 834 L91
    NOP
   L92
    ICONST_0
    ISTORE 23
   L93
    ALOAD 4
    LDC -692256719
    LDC "CC(ReusableComposeNode)P(1,2)376@14062L9:Composables.kt#9igjgp"
   L94
    LINENUMBER 836 L94
    INVOKESTATIC androidx/compose/runtime/ComposerKt.sourceInformationMarkerStart (Landroidx/compose/runtime/Composer;ILjava/lang/String;)V
   L95
    LINENUMBER 837 L95
    ALOAD 4
    INVOKEINTERFACE androidx/compose/runtime/Composer.getApplier ()Landroidx/compose/runtime/Applier; (itf)
    INSTANCEOF androidx/compose/runtime/Applier
    IFNE L96
    INVOKESTATIC androidx/compose/runtime/ComposablesKt.invalidApplier ()V
   L96
    ALOAD 4
   L97
    LINENUMBER 838 L97
    INVOKEINTERFACE androidx/compose/runtime/Composer.startReusableNode ()V (itf)
   L98
    LINENUMBER 839 L98
    ALOAD 4
    INVOKEINTERFACE androidx/compose/runtime/Composer.getInserting ()Z (itf)
    IFEQ L99
    ALOAD 4
   L100
    LINENUMBER 840 L100
    ALOAD 21
    INVOKEINTERFACE androidx/compose/runtime/Composer.createNode (Lkotlin/jvm/functions/Function0;)V (itf)
    GOTO L101
   L99
    ALOAD 4
   L102
    LINENUMBER 842 L102
    INVOKEINTERFACE androidx/compose/runtime/Composer.useNode ()V (itf)
   L101
    LINENUMBER 844 L101
    ALOAD 4
    INVOKESTATIC androidx/compose/runtime/Updater.constructor-impl (Landroidx/compose/runtime/Composer;)Landroidx/compose/runtime/Composer;
    ASTORE 24
   L103
    ICONST_0
    ISTORE 25
   L104
    LINENUMBER 845 L104
    ALOAD 24
    ALOAD 15
    GETSTATIC androidx/compose/ui/node/ComposeUiNode.Companion : Landroidx/compose/ui/node/ComposeUiNode$Companion;
    INVOKEVIRTUAL androidx/compose/ui/node/ComposeUiNode$Companion.getSetMeasurePolicy ()Lkotlin/jvm/functions/Function2;
    INVOKESTATIC androidx/compose/runtime/Updater.set-impl (Landroidx/compose/runtime/Composer;Ljava/lang/Object;Lkotlin/jvm/functions/Function2;)V
   L105
    LINENUMBER 846 L105
    ALOAD 24
    ALOAD 19
    GETSTATIC androidx/compose/ui/node/ComposeUiNode.Companion : Landroidx/compose/ui/node/ComposeUiNode$Companion;
    INVOKEVIRTUAL androidx/compose/ui/node/ComposeUiNode$Companion.getSetResolvedCompositionLocals ()Lkotlin/jvm/functions/Function2;
    INVOKESTATIC androidx/compose/runtime/Updater.set-impl (Landroidx/compose/runtime/Composer;Ljava/lang/Object;Lkotlin/jvm/functions/Function2;)V
   L106
    LINENUMBER 848 L106
    GETSTATIC androidx/compose/ui/node/ComposeUiNode.Companion : Landroidx/compose/ui/node/ComposeUiNode$Companion;
    INVOKEVIRTUAL androidx/compose/ui/node/ComposeUiNode$Companion.getSetCompositeKeyHash ()Lkotlin/jvm/functions/Function2;
    ASTORE 26
   L107
    ICONST_0
    ISTORE 27
   L108
    LINENUMBER 849 L108
    ALOAD 24
    ASTORE 28
   L109
    ICONST_0
    ISTORE 29
   L110
    LINENUMBER 850 L110
    ALOAD 28
    INVOKEINTERFACE androidx/compose/runtime/Composer.getInserting ()Z (itf)
    IFNE L111
    ALOAD 28
    INVOKEINTERFACE androidx/compose/runtime/Composer.rememberedValue ()Ljava/lang/Object; (itf)
    ILOAD 18
    INVOKESTATIC java/lang/Integer.valueOf (I)Ljava/lang/Integer;
    INVOKESTATIC kotlin/jvm/internal/Intrinsics.areEqual (Ljava/lang/Object;Ljava/lang/Object;)Z
    IFNE L112
   L111
    LINENUMBER 851 L111
    ALOAD 28
    ILOAD 18
    INVOKESTATIC java/lang/Integer.valueOf (I)Ljava/lang/Integer;
    INVOKEINTERFACE androidx/compose/runtime/Composer.updateRememberedValue (Ljava/lang/Object;)V (itf)
   L113
    LINENUMBER 852 L113
    ALOAD 24
    ILOAD 18
    INVOKESTATIC java/lang/Integer.valueOf (I)Ljava/lang/Integer;
    ALOAD 26
    INVOKEINTERFACE androidx/compose/runtime/Composer.apply (Ljava/lang/Object;Lkotlin/jvm/functions/Function2;)V (itf)
   L112
    LINENUMBER 854 L112
    NOP
   L114
    LINENUMBER 849 L114
    NOP
   L115
    LINENUMBER 854 L115
    NOP
   L116
    LINENUMBER 855 L116
    ALOAD 24
    ALOAD 20
    GETSTATIC androidx/compose/ui/node/ComposeUiNode.Companion : Landroidx/compose/ui/node/ComposeUiNode$Companion;
    INVOKEVIRTUAL androidx/compose/ui/node/ComposeUiNode$Companion.getSetModifier ()Lkotlin/jvm/functions/Function2;
    INVOKESTATIC androidx/compose/runtime/Updater.set-impl (Landroidx/compose/runtime/Composer;Ljava/lang/Object;Lkotlin/jvm/functions/Function2;)V
   L117
    LINENUMBER 856 L117
    NOP
   L118
    LINENUMBER 844 L118
    NOP
   L119
    LINENUMBER 857 L119
    ALOAD 4
    BIPUSH 14
    ILOAD 22
    BIPUSH 6
    ISHR
    IAND
    ISTORE 30
    ASTORE 31
   L120
    ICONST_0
    ISTORE 32
   L121
    ALOAD 31
    LDC -2146769399
    LDC "C73@3429L9:Box.kt#2w3rfo"
   L122
    LINENUMBER 858 L122
    INVOKESTATIC androidx/compose/runtime/ComposerKt.sourceInformationMarkerStart (Landroidx/compose/runtime/Composer;ILjava/lang/String;)V
    GETSTATIC androidx/compose/foundation/layout/BoxScopeInstance.INSTANCE : Landroidx/compose/foundation/layout/BoxScopeInstance;
    ALOAD 31
    BIPUSH 6
    BIPUSH 112
    ILOAD 13
    BIPUSH 6
    ISHR
    IAND
    IOR
    INVOKESTATIC java/lang/Integer.valueOf (I)Ljava/lang/Integer;
    CHECKCAST java/lang/Number
    INVOKEVIRTUAL java/lang/Number.intValue ()I
    ISTORE 33
    CHECKCAST androidx/compose/runtime/Composer
    ASTORE 34
    CHECKCAST androidx/compose/foundation/layout/BoxScope
    ASTORE 35
    INVOKESTATIC kotlin/jvm/internal/InlineMarker.beforeInlineCall ()V
   L123
    ICONST_0
    ISTORE 36
   L124
    ALOAD 34
    LDC 1999770700
    LDC "C156@9002L269,150@8664L607,166@9295L32:BodySection.kt#q4a1do"
   L125
    LINENUMBER 144 L125
    INVOKESTATIC androidx/compose/runtime/ComposerKt.sourceInformationMarkerStart (Landroidx/compose/runtime/Composer;ILjava/lang/String;)V
    ALOAD 0
    INVOKESTATIC com/skgtecnologia/sisem/ui/sections/BodySectionKt.getStickyFooter (Ljava/util/List;)Lcom/valkiria/uicomponents/components/stepper/StepperUiModel;
    ASTORE 37
   L126
    LINENUMBER 145 L126
    ALOAD 37
    IFNULL L127
   L128
    LINENUMBER 146 L128
    ALOAD 1
    GETSTATIC androidx/compose/ui/Modifier.Companion : Landroidx/compose/ui/Modifier$Companion;
    CHECKCAST androidx/compose/ui/Modifier
    FCONST_0
    FCONST_0
    FCONST_0
    BIPUSH 60
    ISTORE 38
   L129
    ICONST_0
    ISTORE 39
   L130
    LINENUMBER 859 L130
    ILOAD 38
    I2F
    INVOKESTATIC androidx/compose/ui/unit/Dp.constructor-impl (F)F
    GOTO L131
   L131
    LINENUMBER 146 L131
    BIPUSH 7
    ACONST_NULL
    INVOKESTATIC androidx/compose/foundation/layout/PaddingKt.padding-qDBjuR0$default (Landroidx/compose/ui/Modifier;FFFFILjava/lang/Object;)Landroidx/compose/ui/Modifier;
    INVOKEINTERFACE androidx/compose/ui/Modifier.then (Landroidx/compose/ui/Modifier;)Landroidx/compose/ui/Modifier; (itf)
    GOTO L132
   L127
    LINENUMBER 148 L127
    ALOAD 1
   L132
    LINENUMBER 145 L132
    ASTORE 40
   L133
    LINENUMBER 152 L133
    ALOAD 40
   L134
    LINENUMBER 153 L134
    ALOAD 8
   L135
    LINENUMBER 154 L135
    BIPUSH 20
    ISTORE 38
   L136
    ICONST_0
    ISTORE 39
   L137
    LINENUMBER 860 L137
    ILOAD 38
    I2F
    INVOKESTATIC androidx/compose/ui/unit/Dp.constructor-impl (F)F
    GOTO L138
   L138
    LINENUMBER 154 L138
    BIPUSH 8
    ISTORE 38
   L139
    ICONST_0
    ISTORE 39
   L140
    LINENUMBER 860 L140
    ILOAD 38
    I2F
    INVOKESTATIC androidx/compose/ui/unit/Dp.constructor-impl (F)F
    GOTO L141
   L141
    LINENUMBER 154 L141
    INVOKESTATIC androidx/compose/foundation/layout/PaddingKt.PaddingValues-YgX7TsA (FF)Landroidx/compose/foundation/layout/PaddingValues;
    ICONST_0
   L142
    LINENUMBER 155 L142
    GETSTATIC androidx/compose/foundation/layout/Arrangement.INSTANCE : Landroidx/compose/foundation/layout/Arrangement;
    ICONST_0
    ISTORE 38
   L143
    ICONST_0
    ISTORE 39
   L144
    LINENUMBER 861 L144
    ILOAD 38
    I2F
    INVOKESTATIC androidx/compose/ui/unit/Dp.constructor-impl (F)F
    GOTO L145
   L145
    LINENUMBER 155 L145
    GETSTATIC androidx/compose/ui/Alignment.Companion : Landroidx/compose/ui/Alignment$Companion;
    INVOKEVIRTUAL androidx/compose/ui/Alignment$Companion.getTop ()Landroidx/compose/ui/Alignment$Vertical;
    INVOKEVIRTUAL androidx/compose/foundation/layout/Arrangement.spacedBy-D5KLDUw (FLandroidx/compose/ui/Alignment$Vertical;)Landroidx/compose/foundation/layout/Arrangement$Vertical;
   L146
    LINENUMBER 156 L146
    GETSTATIC androidx/compose/ui/Alignment.Companion : Landroidx/compose/ui/Alignment$Companion;
    INVOKEVIRTUAL androidx/compose/ui/Alignment$Companion.getCenterHorizontally ()Landroidx/compose/ui/Alignment$Horizontal;
    ACONST_NULL
    ICONST_0
    ALOAD 34
    LDC -1182400547
    LDC "CC(remember):BodySection.kt#9igjgp"
   L147
    LINENUMBER 157 L147
    INVOKESTATIC androidx/compose/runtime/ComposerKt.sourceInformationMarkerStart (Landroidx/compose/runtime/Composer;ILjava/lang/String;)V
    ALOAD 34
    ASTORE 39
    ALOAD 4
    ALOAD 0
    INVOKEINTERFACE androidx/compose/runtime/Composer.changedInstance (Ljava/lang/Object;)Z (itf)
    ALOAD 4
    ALOAD 8
    INVOKEINTERFACE androidx/compose/runtime/Composer.changed (Ljava/lang/Object;)Z (itf)
    IOR
    ALOAD 4
    ALOAD 9
    INVOKEINTERFACE androidx/compose/runtime/Composer.changedInstance (Ljava/lang/Object;)Z (itf)
    IOR
    ILOAD 7
    SIPUSH 896
    IAND
    SIPUSH 256
    IF_ICMPNE L148
    ICONST_1
    GOTO L149
   L148
    ICONST_0
   L149
    IOR
    ILOAD 7
    SIPUSH 7168
    IAND
    SIPUSH 2048
    IF_ICMPNE L150
    ICONST_1
    GOTO L151
   L150
    ICONST_0
   L151
    IOR
    ISTORE 41
   L152
    ICONST_0
    ISTORE 42
   L153
    LINENUMBER 862 L153
    ALOAD 39
    INVOKEINTERFACE androidx/compose/runtime/Composer.rememberedValue ()Ljava/lang/Object; (itf)
    ASTORE 43
   L154
    ICONST_0
    ISTORE 44
   L155
    LINENUMBER 863 L155
    ILOAD 41
    IFNE L156
    ALOAD 43
    GETSTATIC androidx/compose/runtime/Composer.Companion : Landroidx/compose/runtime/Composer$Companion;
    INVOKEVIRTUAL androidx/compose/runtime/Composer$Companion.getEmpty ()Ljava/lang/Object;
    IF_ACMPNE L157
   L156
    LINENUMBER 864 L156
    ISTORE 45
    ASTORE 46
    ASTORE 47
    ASTORE 48
    ISTORE 49
    ASTORE 50
    ASTORE 51
    ASTORE 52
    ICONST_0
    ISTORE 53
   L158
    LINENUMBER 157 L158
    ALOAD 0
    ALOAD 8
    ALOAD 9
    ILOAD 2
    ALOAD 3
    INVOKEDYNAMIC invoke(Ljava/util/List;Landroidx/compose/foundation/lazy/LazyListState;Lkotlinx/coroutines/CoroutineScope;ZLkotlin/jvm/functions/Function1;)Lkotlin/jvm/functions/Function1; [
      // handle kind 0x6 : INVOKESTATIC
      java/lang/invoke/LambdaMetafactory.metafactory(Ljava/lang/invoke/MethodHandles$Lookup;Ljava/lang/String;Ljava/lang/invoke/MethodType;Ljava/lang/invoke/MethodType;Ljava/lang/invoke/MethodHandle;Ljava/lang/invoke/MethodType;)Ljava/lang/invoke/CallSite;
      // arguments:
      (Ljava/lang/Object;)Ljava/lang/Object;, 
      // handle kind 0x6 : INVOKESTATIC
      com/skgtecnologia/sisem/ui/sections/BodySectionKt.BodySection$lambda$6$lambda$1$lambda$0(Ljava/util/List;Landroidx/compose/foundation/lazy/LazyListState;Lkotlinx/coroutines/CoroutineScope;ZLkotlin/jvm/functions/Function1;Landroidx/compose/foundation/lazy/LazyListScope;)Lkotlin/Unit;, 
      (Landroidx/compose/foundation/lazy/LazyListScope;)Lkotlin/Unit;
    ]
    GOTO L159
   L159
    ASTORE 54
    ALOAD 52
    ALOAD 51
    ALOAD 50
    ILOAD 49
    ALOAD 48
    ALOAD 47
    ALOAD 46
    ILOAD 45
    ALOAD 54
   L160
    LINENUMBER 864 L160
    ASTORE 55
   L161
    LINENUMBER 865 L161
    ALOAD 39
    ALOAD 55
    INVOKEINTERFACE androidx/compose/runtime/Composer.updateRememberedValue (Ljava/lang/Object;)V (itf)
   L162
    LINENUMBER 866 L162
    ALOAD 55
   L163
    GOTO L164
   L157
    LINENUMBER 867 L157
    ALOAD 43
   L164
    LINENUMBER 863 L164
    NOP
   L165
    LINENUMBER 862 L165
    NOP
   L166
    LINENUMBER 862 L166
    GOTO L167
   L167
    LINENUMBER 157 L167
    CHECKCAST kotlin/jvm/functions/Function1
    ASTORE 38
    ALOAD 34
    INVOKESTATIC androidx/compose/runtime/ComposerKt.sourceInformationMarkerEnd (Landroidx/compose/runtime/Composer;)V
    ALOAD 38
    ALOAD 34
    LDC 221568
    SIPUSH 200
   L168
    LINENUMBER 151 L168
    INVOKESTATIC androidx/compose/foundation/lazy/LazyDslKt.LazyColumn (Landroidx/compose/ui/Modifier;Landroidx/compose/foundation/lazy/LazyListState;Landroidx/compose/foundation/layout/PaddingValues;ZLandroidx/compose/foundation/layout/Arrangement$Vertical;Landroidx/compose/ui/Alignment$Horizontal;Landroidx/compose/foundation/gestures/FlingBehavior;ZLkotlin/jvm/functions/Function1;Landroidx/compose/runtime/Composer;II)V
   L169
    LINENUMBER 167 L169
    ALOAD 8
    ALOAD 0
    ALOAD 3
    ALOAD 34
    BIPUSH 112
    ILOAD 7
    ICONST_3
    ISHL
    IAND
    SIPUSH 896
    ILOAD 7
    ICONST_3
    ISHR
    IAND
    IOR
    INVOKESTATIC com/skgtecnologia/sisem/ui/sections/BodySectionKt.HandleListScroll (Landroidx/compose/foundation/lazy/LazyListState;Ljava/util/List;Lkotlin/jvm/functions/Function1;Landroidx/compose/runtime/Composer;I)V
   L170
    LINENUMBER 169 L170
    ALOAD 37
    IFNONNULL L171
    ALOAD 34
    LDC 2000665389
    INVOKEINTERFACE androidx/compose/runtime/Composer.startReplaceGroup (I)V (itf)
    ALOAD 34
    INVOKEINTERFACE androidx/compose/runtime/Composer.endReplaceGroup ()V (itf)
    ACONST_NULL
    CHECKCAST kotlin/Unit
    GOTO L172
   L171
    ALOAD 34
    LDC 2000665390
    INVOKEINTERFACE androidx/compose/runtime/Composer.startReplaceGroup (I)V (itf)
    ALOAD 34
    LDC "*169@9386L1079"
    INVOKESTATIC androidx/compose/runtime/ComposerKt.sourceInformation (Landroidx/compose/runtime/Composer;Ljava/lang/String;)V
    ALOAD 37
    CHECKCAST com/valkiria/uicomponents/components/stepper/StepperUiModel
    ASTORE 39
   L173
    ICONST_0
    ISTORE 41
   L174
    LINENUMBER 171 L174
    ALOAD 35
    GETSTATIC androidx/compose/ui/Modifier.Companion : Landroidx/compose/ui/Modifier$Companion;
    CHECKCAST androidx/compose/ui/Modifier
   L175
    LINENUMBER 172 L175
    FCONST_0
    ICONST_1
    ACONST_NULL
    INVOKESTATIC androidx/compose/foundation/layout/SizeKt.fillMaxWidth$default (Landroidx/compose/ui/Modifier;FILjava/lang/Object;)Landroidx/compose/ui/Modifier;
   L176
    LINENUMBER 173 L176
    GETSTATIC androidx/compose/ui/Alignment.Companion : Landroidx/compose/ui/Alignment$Companion;
    INVOKEVIRTUAL androidx/compose/ui/Alignment$Companion.getBottomCenter ()Landroidx/compose/ui/Alignment;
    INVOKEINTERFACE androidx/compose/foundation/layout/BoxScope.align (Landroidx/compose/ui/Modifier;Landroidx/compose/ui/Alignment;)Landroidx/compose/ui/Modifier; (itf)
    ASTORE 42
    ICONST_0
    ISTORE 43
   L177
    LINENUMBER 170 L177
    NOP
   L178
    ICONST_0
    ISTORE 44
   L179
    ALOAD 34
    LDC -483455358
    LDC "CC(Column)P(2,3,1)86@4330L61,87@4396L133:Column.kt#2w3rfo"
   L180
    LINENUMBER 868 L180
    INVOKESTATIC androidx/compose/runtime/ComposerKt.sourceInformationMarkerStart (Landroidx/compose/runtime/Composer;ILjava/lang/String;)V
   L181
    LINENUMBER 869 L181
    GETSTATIC androidx/compose/foundation/layout/Arrangement.INSTANCE : Landroidx/compose/foundation/layout/Arrangement;
    INVOKEVIRTUAL androidx/compose/foundation/layout/Arrangement.getTop ()Landroidx/compose/foundation/layout/Arrangement$Vertical;
    ASTORE 53
   L182
    LINENUMBER 870 L182
    GETSTATIC androidx/compose/ui/Alignment.Companion : Landroidx/compose/ui/Alignment$Companion;
    INVOKEVIRTUAL androidx/compose/ui/Alignment$Companion.getStart ()Landroidx/compose/ui/Alignment$Horizontal;
    ASTORE 55
   L183
    LINENUMBER 873 L183
    ALOAD 53
    ALOAD 55
    ALOAD 34
    BIPUSH 14
    ILOAD 43
    ICONST_3
    ISHR
    IAND
    BIPUSH 112
    ILOAD 43
    ICONST_3
    ISHR
    IAND
    IOR
    INVOKESTATIC androidx/compose/foundation/layout/ColumnKt.columnMeasurePolicy (Landroidx/compose/foundation/layout/Arrangement$Vertical;Landroidx/compose/ui/Alignment$Horizontal;Landroidx/compose/runtime/Composer;I)Landroidx/compose/ui/layout/MeasurePolicy;
    ASTORE 56
   L184
    BIPUSH 112
    ILOAD 43
    ICONST_3
    ISHL
    IAND
    ISTORE 57
   L185
    LINENUMBER 874 L185
    NOP
   L186
    ICONST_0
    ISTORE 58
   L187
    ALOAD 34
    LDC -1323940314
    LDC "CC(Layout)P(!1,2)79@3208L23,82@3359L411:Layout.kt#80mrfh"
   L188
    LINENUMBER 875 L188
    INVOKESTATIC androidx/compose/runtime/ComposerKt.sourceInformationMarkerStart (Landroidx/compose/runtime/Composer;ILjava/lang/String;)V
    ALOAD 34
    ICONST_0
   L189
    LINENUMBER 876 L189
    INVOKESTATIC androidx/compose/runtime/ComposablesKt.getCurrentCompositeKeyHash (Landroidx/compose/runtime/Composer;I)I
    ISTORE 59
   L190
    ALOAD 34
   L191
    LINENUMBER 877 L191
    INVOKEINTERFACE androidx/compose/runtime/Composer.getCurrentCompositionLocalMap ()Landroidx/compose/runtime/CompositionLocalMap; (itf)
    ASTORE 60
   L192
    ALOAD 34
   L193
    LINENUMBER 878 L193
    ALOAD 42
    INVOKESTATIC androidx/compose/ui/ComposedModifierKt.materializeModifier (Landroidx/compose/runtime/Composer;Landroidx/compose/ui/Modifier;)Landroidx/compose/ui/Modifier;
    ASTORE 61
   L194
    LINENUMBER 880 L194
    GETSTATIC androidx/compose/ui/node/ComposeUiNode.Companion : Landroidx/compose/ui/node/ComposeUiNode$Companion;
    INVOKEVIRTUAL androidx/compose/ui/node/ComposeUiNode$Companion.getConstructor ()Lkotlin/jvm/functions/Function0;
    ASTORE 62
    BIPUSH 6
    SIPUSH 896
    ILOAD 57
    BIPUSH 6
    ISHL
    IAND
    IOR
    ISTORE 63
   L195
    LINENUMBER 879 L195
    NOP
   L196
    ICONST_0
    ISTORE 64
   L197
    ALOAD 34
    LDC -692256719
    LDC "CC(ReusableComposeNode)P(1,2)376@14062L9:Composables.kt#9igjgp"
   L198
    LINENUMBER 881 L198
    INVOKESTATIC androidx/compose/runtime/ComposerKt.sourceInformationMarkerStart (Landroidx/compose/runtime/Composer;ILjava/lang/String;)V
   L199
    LINENUMBER 882 L199
    ALOAD 34
    INVOKEINTERFACE androidx/compose/runtime/Composer.getApplier ()Landroidx/compose/runtime/Applier; (itf)
    INSTANCEOF androidx/compose/runtime/Applier
    IFNE L200
    INVOKESTATIC androidx/compose/runtime/ComposablesKt.invalidApplier ()V
   L200
    ALOAD 34
   L201
    LINENUMBER 883 L201
    INVOKEINTERFACE androidx/compose/runtime/Composer.startReusableNode ()V (itf)
   L202
    LINENUMBER 884 L202
    ALOAD 34
    INVOKEINTERFACE androidx/compose/runtime/Composer.getInserting ()Z (itf)
    IFEQ L203
    ALOAD 34
   L204
    LINENUMBER 885 L204
    ALOAD 62
    INVOKEINTERFACE androidx/compose/runtime/Composer.createNode (Lkotlin/jvm/functions/Function0;)V (itf)
    GOTO L205
   L203
    ALOAD 34
   L206
    LINENUMBER 887 L206
    INVOKEINTERFACE androidx/compose/runtime/Composer.useNode ()V (itf)
   L205
    LINENUMBER 889 L205
    ALOAD 34
    INVOKESTATIC androidx/compose/runtime/Updater.constructor-impl (Landroidx/compose/runtime/Composer;)Landroidx/compose/runtime/Composer;
    ASTORE 65
   L207
    ICONST_0
    ISTORE 66
   L208
    LINENUMBER 890 L208
    ALOAD 65
    ALOAD 56
    GETSTATIC androidx/compose/ui/node/ComposeUiNode.Companion : Landroidx/compose/ui/node/ComposeUiNode$Companion;
    INVOKEVIRTUAL androidx/compose/ui/node/ComposeUiNode$Companion.getSetMeasurePolicy ()Lkotlin/jvm/functions/Function2;
    INVOKESTATIC androidx/compose/runtime/Updater.set-impl (Landroidx/compose/runtime/Composer;Ljava/lang/Object;Lkotlin/jvm/functions/Function2;)V
   L209
    LINENUMBER 891 L209
    ALOAD 65
    ALOAD 60
    GETSTATIC androidx/compose/ui/node/ComposeUiNode.Companion : Landroidx/compose/ui/node/ComposeUiNode$Companion;
    INVOKEVIRTUAL androidx/compose/ui/node/ComposeUiNode$Companion.getSetResolvedCompositionLocals ()Lkotlin/jvm/functions/Function2;
    INVOKESTATIC androidx/compose/runtime/Updater.set-impl (Landroidx/compose/runtime/Composer;Ljava/lang/Object;Lkotlin/jvm/functions/Function2;)V
   L210
    LINENUMBER 893 L210
    GETSTATIC androidx/compose/ui/node/ComposeUiNode.Companion : Landroidx/compose/ui/node/ComposeUiNode$Companion;
    INVOKEVIRTUAL androidx/compose/ui/node/ComposeUiNode$Companion.getSetCompositeKeyHash ()Lkotlin/jvm/functions/Function2;
    ASTORE 67
   L211
    ICONST_0
    ISTORE 68
   L212
    LINENUMBER 894 L212
    ALOAD 65
    ASTORE 69
   L213
    ICONST_0
    ISTORE 70
   L214
    LINENUMBER 895 L214
    ALOAD 69
    INVOKEINTERFACE androidx/compose/runtime/Composer.getInserting ()Z (itf)
    IFNE L215
    ALOAD 69
    INVOKEINTERFACE androidx/compose/runtime/Composer.rememberedValue ()Ljava/lang/Object; (itf)
    ILOAD 59
    INVOKESTATIC java/lang/Integer.valueOf (I)Ljava/lang/Integer;
    INVOKESTATIC kotlin/jvm/internal/Intrinsics.areEqual (Ljava/lang/Object;Ljava/lang/Object;)Z
    IFNE L216
   L215
    LINENUMBER 896 L215
    ALOAD 69
    ILOAD 59
    INVOKESTATIC java/lang/Integer.valueOf (I)Ljava/lang/Integer;
    INVOKEINTERFACE androidx/compose/runtime/Composer.updateRememberedValue (Ljava/lang/Object;)V (itf)
   L217
    LINENUMBER 897 L217
    ALOAD 65
    ILOAD 59
    INVOKESTATIC java/lang/Integer.valueOf (I)Ljava/lang/Integer;
    ALOAD 67
    INVOKEINTERFACE androidx/compose/runtime/Composer.apply (Ljava/lang/Object;Lkotlin/jvm/functions/Function2;)V (itf)
   L216
    LINENUMBER 899 L216
    NOP
   L218
    LINENUMBER 894 L218
    NOP
   L219
    LINENUMBER 899 L219
    NOP
   L220
    LINENUMBER 900 L220
    ALOAD 65
    ALOAD 61
    GETSTATIC androidx/compose/ui/node/ComposeUiNode.Companion : Landroidx/compose/ui/node/ComposeUiNode$Companion;
    INVOKEVIRTUAL androidx/compose/ui/node/ComposeUiNode$Companion.getSetModifier ()Lkotlin/jvm/functions/Function2;
    INVOKESTATIC androidx/compose/runtime/Updater.set-impl (Landroidx/compose/runtime/Composer;Ljava/lang/Object;Lkotlin/jvm/functions/Function2;)V
   L221
    LINENUMBER 901 L221
    NOP
   L222
    LINENUMBER 889 L222
    NOP
   L223
    LINENUMBER 902 L223
    ALOAD 34
    BIPUSH 14
    ILOAD 63
    BIPUSH 6
    ISHR
    IAND
    ISTORE 71
    ASTORE 72
   L224
    ICONST_0
    ISTORE 73
   L225
    ALOAD 72
    LDC -384784025
    LDC "C88@4444L9:Column.kt#2w3rfo"
   L226
    LINENUMBER 903 L226
    INVOKESTATIC androidx/compose/runtime/ComposerKt.sourceInformationMarkerStart (Landroidx/compose/runtime/Composer;ILjava/lang/String;)V
    GETSTATIC androidx/compose/foundation/layout/ColumnScopeInstance.INSTANCE : Landroidx/compose/foundation/layout/ColumnScopeInstance;
    ALOAD 72
    BIPUSH 6
    BIPUSH 112
    ILOAD 43
    BIPUSH 6
    ISHR
    IAND
    IOR
    INVOKESTATIC java/lang/Integer.valueOf (I)Ljava/lang/Integer;
    CHECKCAST java/lang/Number
    INVOKEVIRTUAL java/lang/Number.intValue ()I
    ISTORE 74
    CHECKCAST androidx/compose/runtime/Composer
    ASTORE 75
    CHECKCAST androidx/compose/foundation/layout/ColumnScope
    ASTORE 76
   L227
    ICONST_0
    ISTORE 77
   L228
    ALOAD 75
    LDC 389004519
    LDC "C174@9603L844,174@9569L878:BodySection.kt#q4a1do"
   L229
    LINENUMBER 175 L229
    INVOKESTATIC androidx/compose/runtime/ComposerKt.sourceInformationMarkerStart (Landroidx/compose/runtime/Composer;ILjava/lang/String;)V
    ALOAD 39
    ALOAD 75
    LDC -818734406
    LDC "CC(remember):BodySection.kt#9igjgp"
    INVOKESTATIC androidx/compose/runtime/ComposerKt.sourceInformationMarkerStart (Landroidx/compose/runtime/Composer;ILjava/lang/String;)V
    ALOAD 75
    ASTORE 78
    ALOAD 4
    ALOAD 9
    INVOKEINTERFACE androidx/compose/runtime/Composer.changedInstance (Ljava/lang/Object;)Z (itf)
    ALOAD 4
    ALOAD 39
    INVOKEINTERFACE androidx/compose/runtime/Composer.changedInstance (Ljava/lang/Object;)Z (itf)
    IOR
    ALOAD 4
    ALOAD 0
    INVOKEINTERFACE androidx/compose/runtime/Composer.changedInstance (Ljava/lang/Object;)Z (itf)
    IOR
    ALOAD 4
    ALOAD 8
    INVOKEINTERFACE androidx/compose/runtime/Composer.changed (Ljava/lang/Object;)Z (itf)
    IOR
    ILOAD 7
    SIPUSH 7168
    IAND
    SIPUSH 2048
    IF_ICMPNE L230
    ICONST_1
    GOTO L231
   L230
    ICONST_0
   L231
    IOR
    ISTORE 79
   L232
    ICONST_0
    ISTORE 80
   L233
    LINENUMBER 904 L233
    ALOAD 78
    INVOKEINTERFACE androidx/compose/runtime/Composer.rememberedValue ()Ljava/lang/Object; (itf)
    ASTORE 81
   L234
    ICONST_0
    ISTORE 82
   L235
    LINENUMBER 905 L235
    ILOAD 79
    IFNE L236
    ALOAD 81
    GETSTATIC androidx/compose/runtime/Composer.Companion : Landroidx/compose/runtime/Composer$Companion;
    INVOKEVIRTUAL androidx/compose/runtime/Composer$Companion.getEmpty ()Ljava/lang/Object;
    IF_ACMPNE L237
   L236
    LINENUMBER 906 L236
    ASTORE 83
    ICONST_0
    ISTORE 84
   L238
    LINENUMBER 175 L238
    ALOAD 9
    ALOAD 3
    ALOAD 39
    ALOAD 0
    ALOAD 8
    INVOKEDYNAMIC invoke(Lkotlinx/coroutines/CoroutineScope;Lkotlin/jvm/functions/Function1;Lcom/valkiria/uicomponents/components/stepper/StepperUiModel;Ljava/util/List;Landroidx/compose/foundation/lazy/LazyListState;)Lkotlin/jvm/functions/Function1; [
      // handle kind 0x6 : INVOKESTATIC
      java/lang/invoke/LambdaMetafactory.metafactory(Ljava/lang/invoke/MethodHandles$Lookup;Ljava/lang/String;Ljava/lang/invoke/MethodType;Ljava/lang/invoke/MethodType;Ljava/lang/invoke/MethodHandle;Ljava/lang/invoke/MethodType;)Ljava/lang/invoke/CallSite;
      // arguments:
      (Ljava/lang/Object;)Ljava/lang/Object;, 
      // handle kind 0x6 : INVOKESTATIC
      com/skgtecnologia/sisem/ui/sections/BodySectionKt.BodySection$lambda$6$lambda$5$lambda$4$lambda$3$lambda$2(Lkotlinx/coroutines/CoroutineScope;Lkotlin/jvm/functions/Function1;Lcom/valkiria/uicomponents/components/stepper/StepperUiModel;Ljava/util/List;Landroidx/compose/foundation/lazy/LazyListState;Ljava/lang/Integer;)Lkotlin/Unit;, 
      (Ljava/lang/Integer;)Lkotlin/Unit;
    ]
    GOTO L239
   L239
    ALOAD 83
    SWAP
   L240
    LINENUMBER 906 L240
    ASTORE 85
   L241
    LINENUMBER 907 L241
    ALOAD 78
    ALOAD 85
    INVOKEINTERFACE androidx/compose/runtime/Composer.updateRememberedValue (Ljava/lang/Object;)V (itf)
   L242
    LINENUMBER 908 L242
    ALOAD 85
   L243
    GOTO L244
   L237
    LINENUMBER 909 L237
    ALOAD 81
   L244
    LINENUMBER 905 L244
    NOP
   L245
    LINENUMBER 904 L245
    NOP
   L246
    LINENUMBER 904 L246
    GOTO L247
   L247
    LINENUMBER 175 L247
    CHECKCAST kotlin/jvm/functions/Function1
    ASTORE 86
    ALOAD 75
    INVOKESTATIC androidx/compose/runtime/ComposerKt.sourceInformationMarkerEnd (Landroidx/compose/runtime/Composer;)V
    ALOAD 86
    ALOAD 75
    GETSTATIC com/valkiria/uicomponents/components/stepper/StepperUiModel.$stable : I
    INVOKESTATIC com/valkiria/uicomponents/components/stepper/StepperComponentKt.StepperComponent (Lcom/valkiria/uicomponents/components/stepper/StepperUiModel;Lkotlin/jvm/functions/Function1;Landroidx/compose/runtime/Composer;I)V
    ALOAD 75
    INVOKESTATIC androidx/compose/runtime/ComposerKt.sourceInformationMarkerEnd (Landroidx/compose/runtime/Composer;)V
   L248
    LINENUMBER 195 L248
    GOTO L249
   L249
    GETSTATIC kotlin/Unit.INSTANCE : Lkotlin/Unit;
   L250
    LINENUMBER 903 L250
    POP
    ALOAD 72
    INVOKESTATIC androidx/compose/runtime/ComposerKt.sourceInformationMarkerEnd (Landroidx/compose/runtime/Composer;)V
   L251
    LINENUMBER 902 L251
    ALOAD 34
   L252
    LINENUMBER 910 L252
    INVOKEINTERFACE androidx/compose/runtime/Composer.endNode ()V (itf)
    ALOAD 34
   L253
    LINENUMBER 881 L253
    INVOKESTATIC androidx/compose/runtime/ComposerKt.sourceInformationMarkerEnd (Landroidx/compose/runtime/Composer;)V
   L254
    LINENUMBER 911 L254
    NOP
   L255
    ALOAD 34
   L256
    LINENUMBER 875 L256
    INVOKESTATIC androidx/compose/runtime/ComposerKt.sourceInformationMarkerEnd (Landroidx/compose/runtime/Composer;)V
   L257
    LINENUMBER 912 L257
    NOP
   L258
    ALOAD 34
   L259
    LINENUMBER 868 L259
    INVOKESTATIC androidx/compose/runtime/ComposerKt.sourceInformationMarkerEnd (Landroidx/compose/runtime/Composer;)V
   L260
    LINENUMBER 913 L260
    GOTO L261
   L261
    LINENUMBER 196 L261
    GOTO L262
   L262
    GETSTATIC kotlin/Unit.INSTANCE : Lkotlin/Unit;
   L263
    LINENUMBER 169 L263
    GOTO L264
   L264
    POP
   L265
    LINENUMBER 169 L265
    ALOAD 34
    INVOKEINTERFACE androidx/compose/runtime/Composer.endReplaceGroup ()V (itf)
    GETSTATIC kotlin/Unit.INSTANCE : Lkotlin/Unit;
   L172
    POP
    ALOAD 34
   L266
    LINENUMBER 144 L266
    INVOKESTATIC androidx/compose/runtime/ComposerKt.sourceInformationMarkerEnd (Landroidx/compose/runtime/Composer;)V
   L267
    LINENUMBER 197 L267
    NOP
    GOTO L268
   L268
    GETSTATIC kotlin/Unit.INSTANCE : Lkotlin/Unit;
    INVOKESTATIC kotlin/jvm/internal/InlineMarker.afterInlineCall ()V
   L269
    LINENUMBER 858 L269
    POP
    ALOAD 31
    INVOKESTATIC androidx/compose/runtime/ComposerKt.sourceInformationMarkerEnd (Landroidx/compose/runtime/Composer;)V
   L270
    LINENUMBER 857 L270
    ALOAD 4
   L271
    LINENUMBER 914 L271
    INVOKEINTERFACE androidx/compose/runtime/Composer.endNode ()V (itf)
    ALOAD 4
   L272
    LINENUMBER 836 L272
    INVOKESTATIC androidx/compose/runtime/ComposerKt.sourceInformationMarkerEnd (Landroidx/compose/runtime/Composer;)V
   L273
    LINENUMBER 915 L273
    NOP
   L274
    ALOAD 4
   L275
    LINENUMBER 830 L275
    INVOKESTATIC androidx/compose/runtime/ComposerKt.sourceInformationMarkerEnd (Landroidx/compose/runtime/Composer;)V
   L276
    LINENUMBER 916 L276
    NOP
   L277
    ALOAD 4
   L278
    LINENUMBER 823 L278
    INVOKESTATIC androidx/compose/runtime/ComposerKt.sourceInformationMarkerEnd (Landroidx/compose/runtime/Composer;)V
   L279
    LINENUMBER 917 L279
    NOP
    GOTO L280
   L280
    LINENUMBER 142 L280
    ALOAD 4
    INVOKEINTERFACE androidx/compose/runtime/Composer.endReplaceGroup ()V (itf)
    GOTO L281
   L72
    LINENUMBER 198 L72
    ALOAD 4
    LDC -2119068367
    INVOKEINTERFACE androidx/compose/runtime/Composer.startReplaceGroup (I)V (itf)
    ALOAD 4
    INVOKEINTERFACE androidx/compose/runtime/Composer.endReplaceGroup ()V (itf)
   L281
    INVOKESTATIC androidx/compose/runtime/ComposerKt.isTraceInProgress ()Z
    IFEQ L282
    INVOKESTATIC androidx/compose/runtime/ComposerKt.traceEventEnd ()V
   L282
    GOTO L283
   L20
    LINENUMBER 199 L20
    ALOAD 4
    INVOKEINTERFACE androidx/compose/runtime/Composer.skipToGroupEnd ()V (itf)
   L283
    ALOAD 4
    INVOKEINTERFACE androidx/compose/runtime/Composer.endRestartGroup ()Landroidx/compose/runtime/ScopeUpdateScope; (itf)
    ASTORE 8
   L284
    ALOAD 8
    IFNULL L285
    ALOAD 8
    ALOAD 0
    ALOAD 1
    ILOAD 2
    ALOAD 3
    ILOAD 5
    ILOAD 6
    INVOKEDYNAMIC invoke(Ljava/util/List;Landroidx/compose/ui/Modifier;ZLkotlin/jvm/functions/Function1;II)Lkotlin/jvm/functions/Function2; [
      // handle kind 0x6 : INVOKESTATIC
      java/lang/invoke/LambdaMetafactory.metafactory(Ljava/lang/invoke/MethodHandles$Lookup;Ljava/lang/String;Ljava/lang/invoke/MethodType;Ljava/lang/invoke/MethodType;Ljava/lang/invoke/MethodHandle;Ljava/lang/invoke/MethodType;)Ljava/lang/invoke/CallSite;
      // arguments:
      (Ljava/lang/Object;Ljava/lang/Object;)Ljava/lang/Object;, 
      // handle kind 0x6 : INVOKESTATIC
      com/skgtecnologia/sisem/ui/sections/BodySectionKt.BodySection$lambda$7(Ljava/util/List;Landroidx/compose/ui/Modifier;ZLkotlin/jvm/functions/Function1;IILandroidx/compose/runtime/Composer;I)Lkotlin/Unit;, 
      (Landroidx/compose/runtime/Composer;Ljava/lang/Integer;)Lkotlin/Unit;
    ]
    INVOKEINTERFACE androidx/compose/runtime/ScopeUpdateScope.updateScope (Lkotlin/jvm/functions/Function2;)V (itf)
    GOTO L286
   L285
    NOP
   L286
    NOP
    RETURN
   L287
    LOCALVARIABLE $i$a$-rememberCoroutineScope-EffectsKt$rememberCoroutineScope$1 I L45 L48 20
    LOCALVARIABLE $i$a$-cache-EffectsKt$rememberCoroutineScope$wrapper$1$iv I L43 L51 19
    LOCALVARIABLE value$iv$iv Ljava/lang/Object; L52 L54 20
    LOCALVARIABLE $i$a$-let-ComposerKt$cache$1$iv$iv I L40 L56 18
    LOCALVARIABLE it$iv$iv Ljava/lang/Object; L39 L56 17
    LOCALVARIABLE $i$f$cache I L38 L58 16
    LOCALVARIABLE $this$cache$iv$iv Landroidx/compose/runtime/Composer; L37 L58 14
    LOCALVARIABLE invalid$iv$iv Z L37 L58 15
    LOCALVARIABLE $i$f$rememberCoroutineScope I L31 L62 12
    LOCALVARIABLE composer$iv Landroidx/compose/runtime/Composer; L35 L62 13
    LOCALVARIABLE wrapper$iv Landroidx/compose/runtime/CompositionScopedCoroutineScopeCanceller; L59 L62 22
    LOCALVARIABLE $changed$iv I L30 L62 11
    LOCALVARIABLE $i$f$getDp I L130 L131 39
    LOCALVARIABLE $this$dp$iv I L129 L131 38
    LOCALVARIABLE $i$f$getDp I L137 L138 39
    LOCALVARIABLE $this$dp$iv I L136 L138 38
    LOCALVARIABLE $i$f$getDp I L140 L141 39
    LOCALVARIABLE $this$dp$iv I L139 L141 38
    LOCALVARIABLE $i$f$getDp I L144 L145 39
    LOCALVARIABLE $this$dp$iv I L143 L145 38
    LOCALVARIABLE $i$a$-cache-BodySectionKt$BodySection$1$1 I L158 L159 53
    LOCALVARIABLE value$iv Ljava/lang/Object; L161 L163 55
    LOCALVARIABLE $i$a$-let-ComposerKt$cache$1$iv I L155 L165 44
    LOCALVARIABLE it$iv Ljava/lang/Object; L154 L165 43
    LOCALVARIABLE $i$f$cache I L153 L167 42
    LOCALVARIABLE $this$cache$iv Landroidx/compose/runtime/Composer; L152 L167 39
    LOCALVARIABLE invalid$iv Z L152 L167 41
    LOCALVARIABLE $i$a$-cache-BodySectionKt$BodySection$1$2$1$1 I L238 L239 84
    LOCALVARIABLE value$iv Ljava/lang/Object; L241 L243 85
    LOCALVARIABLE $i$a$-let-ComposerKt$cache$1$iv I L235 L245 82
    LOCALVARIABLE it$iv Ljava/lang/Object; L234 L245 81
    LOCALVARIABLE $i$f$cache I L233 L247 80
    LOCALVARIABLE $this$cache$iv Landroidx/compose/runtime/Composer; L232 L247 78
    LOCALVARIABLE invalid$iv Z L232 L247 79
    LOCALVARIABLE $i$a$-Column-BodySectionKt$BodySection$1$2$1 I L228 L249 77
    LOCALVARIABLE $this$BodySection_u24lambda_u246_u24lambda_u245_u24lambda_u244 Landroidx/compose/foundation/layout/ColumnScope; L227 L249 76
    LOCALVARIABLE $composer Landroidx/compose/runtime/Composer; L227 L249 75
    LOCALVARIABLE $changed I L227 L249 74
    LOCALVARIABLE $i$a$-Layout-ColumnKt$Column$1$iv I L225 L251 73
    LOCALVARIABLE $composer$iv Landroidx/compose/runtime/Composer; L224 L251 72
    LOCALVARIABLE $changed$iv I L224 L251 71
    LOCALVARIABLE $i$a$-with-Updater$set$1$iv$iv$iv I L214 L218 70
    LOCALVARIABLE $this$set_impl_u24lambda_u240$iv$iv$iv Landroidx/compose/runtime/Composer; L213 L218 69
    LOCALVARIABLE $i$f$set-impl I L212 L220 68
    LOCALVARIABLE block$iv$iv$iv Lkotlin/jvm/functions/Function2; L211 L220 67
    LOCALVARIABLE $i$a$-ReusableComposeNode-LayoutKt$Layout$1$iv$iv I L208 L222 66
    LOCALVARIABLE $this$Layout_u24lambda_u240$iv$iv Landroidx/compose/runtime/Composer; L207 L222 65
    LOCALVARIABLE $i$f$ReusableComposeNode I L197 L255 64
    LOCALVARIABLE factory$iv$iv$iv Lkotlin/jvm/functions/Function0; L196 L255 62
    LOCALVARIABLE $changed$iv$iv$iv I L196 L255 63
    LOCALVARIABLE $i$f$Layout I L187 L258 58
    LOCALVARIABLE compositeKeyHash$iv$iv I L190 L258 59
    LOCALVARIABLE localMap$iv$iv Landroidx/compose/runtime/CompositionLocalMap; L192 L258 60
    LOCALVARIABLE materialized$iv$iv Landroidx/compose/ui/Modifier; L194 L258 61
    LOCALVARIABLE $changed$iv$iv I L186 L258 57
    LOCALVARIABLE $i$f$Column I L179 L261 44
    LOCALVARIABLE measurePolicy$iv Landroidx/compose/ui/layout/MeasurePolicy; L184 L261 56
    LOCALVARIABLE modifier$iv Landroidx/compose/ui/Modifier; L178 L261 42
    LOCALVARIABLE verticalArrangement$iv Landroidx/compose/foundation/layout/Arrangement$Vertical; L182 L261 53
    LOCALVARIABLE horizontalAlignment$iv Landroidx/compose/ui/Alignment$Horizontal; L183 L261 55
    LOCALVARIABLE $changed$iv I L178 L261 43
    LOCALVARIABLE $i$a$-let-BodySectionKt$BodySection$1$2 I L174 L262 41
    LOCALVARIABLE model Lcom/valkiria/uicomponents/components/stepper/StepperUiModel; L173 L262 39
    LOCALVARIABLE stickyFooter Lcom/valkiria/uicomponents/components/stepper/StepperUiModel; L126 L267 37
    LOCALVARIABLE updatedModifier Landroidx/compose/ui/Modifier; L133 L267 40
    LOCALVARIABLE $i$a$-Box-BodySectionKt$BodySection$1 I L124 L268 36
    LOCALVARIABLE $this$BodySection_u24lambda_u246 Landroidx/compose/foundation/layout/BoxScope; L123 L268 35
    LOCALVARIABLE $composer Landroidx/compose/runtime/Composer; L123 L268 34
    LOCALVARIABLE $changed I L123 L268 33
    LOCALVARIABLE $i$a$-Layout-BoxKt$Box$1$iv I L121 L270 32
    LOCALVARIABLE $composer$iv Landroidx/compose/runtime/Composer; L120 L270 31
    LOCALVARIABLE $changed$iv I L120 L270 30
    LOCALVARIABLE $i$a$-with-Updater$set$1$iv$iv$iv I L110 L114 29
    LOCALVARIABLE $this$set_impl_u24lambda_u240$iv$iv$iv Landroidx/compose/runtime/Composer; L109 L114 28
    LOCALVARIABLE $i$f$set-impl I L108 L116 27
    LOCALVARIABLE block$iv$iv$iv Lkotlin/jvm/functions/Function2; L107 L116 26
    LOCALVARIABLE $i$a$-ReusableComposeNode-LayoutKt$Layout$1$iv$iv I L104 L118 25
    LOCALVARIABLE $this$Layout_u24lambda_u240$iv$iv Landroidx/compose/runtime/Composer; L103 L118 24
    LOCALVARIABLE $i$f$ReusableComposeNode I L93 L274 23
    LOCALVARIABLE factory$iv$iv$iv Lkotlin/jvm/functions/Function0; L92 L274 21
    LOCALVARIABLE $changed$iv$iv$iv I L92 L274 22
    LOCALVARIABLE $i$f$Layout I L83 L277 17
    LOCALVARIABLE compositeKeyHash$iv$iv I L86 L277 18
    LOCALVARIABLE localMap$iv$iv Landroidx/compose/runtime/CompositionLocalMap; L88 L277 19
    LOCALVARIABLE materialized$iv$iv Landroidx/compose/ui/Modifier; L90 L277 20
    LOCALVARIABLE $changed$iv$iv I L82 L277 16
    LOCALVARIABLE $i$f$Box I L75 L280 14
    LOCALVARIABLE measurePolicy$iv Landroidx/compose/ui/layout/MeasurePolicy; L80 L280 15
    LOCALVARIABLE modifier$iv Landroidx/compose/ui/Modifier; L74 L280 10
    LOCALVARIABLE contentAlignment$iv Landroidx/compose/ui/Alignment; L78 L280 11
    LOCALVARIABLE propagateMinConstraints$iv Z L79 L280 12
    LOCALVARIABLE $changed$iv I L74 L280 13
    LOCALVARIABLE listState Landroidx/compose/foundation/lazy/LazyListState; L28 L282 8
    LOCALVARIABLE scope Lkotlinx/coroutines/CoroutineScope; L63 L282 9
    LOCALVARIABLE $dirty I L2 L287 7
    LOCALVARIABLE body Ljava/util/List; L0 L287 0
    LOCALVARIABLE modifier Landroidx/compose/ui/Modifier; L0 L287 1
    LOCALVARIABLE validateFields Z L0 L287 2
    LOCALVARIABLE onAction Lkotlin/jvm/functions/Function1; L0 L287 3
    LOCALVARIABLE $composer Landroidx/compose/runtime/Composer; L0 L287 4
    LOCALVARIABLE $changed I L0 L287 5
    MAXSTACK = 12
    MAXLOCALS = 87

File is unknown
The root cause java.lang.OutOfMemoryError was thrown at: org.jetbrains.org.objectweb.asm.tree.analysis.Frame.<init>(Frame.java:78)
	at org.jetbrains.kotlin.codegen.TransformationMethodVisitor.visitEnd(TransformationMethodVisitor.kt:89)
	at org.jetbrains.org.objectweb.asm.MethodVisitor.visitEnd(MethodVisitor.java:783)
	at org.jetbrains.org.objectweb.asm.tree.MethodNode.accept(MethodNode.java:772)
	at org.jetbrains.kotlin.backend.jvm.codegen.ClassCodegen.generateMethod(ClassCodegen.kt:453)
	at org.jetbrains.kotlin.backend.jvm.codegen.ClassCodegen.generate(ClassCodegen.kt:168)
	at org.jetbrains.kotlin.backend.jvm.FileCodegen.lower(JvmPhases.kt:39)
	at org.jetbrains.kotlin.backend.common.phaser.PhaseFactoriesKt.createFilePhase$lambda$4(PhaseFactories.kt:71)
	at org.jetbrains.kotlin.backend.common.phaser.PhaseBuildersKt$createSimpleNamedCompilerPhase$1.phaseBody(PhaseBuilders.kt:69)
	at org.jetbrains.kotlin.backend.common.phaser.SimpleNamedCompilerPhase.phaseBody(CompilerPhase.kt:226)
	at org.jetbrains.kotlin.backend.common.phaser.AbstractNamedCompilerPhase.invoke(CompilerPhase.kt:113)
	at org.jetbrains.kotlin.backend.common.phaser.PerformByIrFilePhase.invokeSequential(performByIrFile.kt:62)
	at org.jetbrains.kotlin.backend.common.phaser.PerformByIrFilePhase.invoke(performByIrFile.kt:52)
	at org.jetbrains.kotlin.backend.common.phaser.PerformByIrFilePhase.invoke(performByIrFile.kt:38)
	at org.jetbrains.kotlin.backend.common.phaser.NamedCompilerPhase.phaseBody(CompilerPhase.kt:166)
	at org.jetbrains.kotlin.backend.common.phaser.AbstractNamedCompilerPhase.invoke(CompilerPhase.kt:113)
	at org.jetbrains.kotlin.backend.common.phaser.CompositePhase.invoke(PhaseBuilders.kt:27)
	at org.jetbrains.kotlin.backend.common.phaser.CompositePhase.invoke(PhaseBuilders.kt:14)
	at org.jetbrains.kotlin.backend.common.phaser.NamedCompilerPhase.phaseBody(CompilerPhase.kt:166)
	at org.jetbrains.kotlin.backend.common.phaser.AbstractNamedCompilerPhase.invoke(CompilerPhase.kt:113)
	at org.jetbrains.kotlin.backend.common.phaser.CompilerPhaseKt.invokeToplevel(CompilerPhase.kt:62)
	at org.jetbrains.kotlin.backend.jvm.JvmIrCodegenFactory.invokeCodegen(JvmIrCodegenFactory.kt:371)
	at org.jetbrains.kotlin.codegen.CodegenFactory.generateModule(CodegenFactory.kt:47)
	at org.jetbrains.kotlin.backend.jvm.JvmIrCodegenFactory.generateModuleInFrontendIRMode(JvmIrCodegenFactory.kt:433)
	at org.jetbrains.kotlin.cli.jvm.compiler.pipeline.JvmCompilerPipelineKt.generateCodeFromIr(jvmCompilerPipeline.kt:246)
	at org.jetbrains.kotlin.cli.jvm.compiler.pipeline.JvmCompilerPipelineKt.compileModulesUsingFrontendIrAndLightTree(jvmCompilerPipeline.kt:142)
	at org.jetbrains.kotlin.cli.jvm.K2JVMCompiler.doExecute(K2JVMCompiler.kt:148)
	at org.jetbrains.kotlin.cli.jvm.K2JVMCompiler.doExecute(K2JVMCompiler.kt:43)
	at org.jetbrains.kotlin.cli.common.CLICompiler.execImpl(CLICompiler.kt:103)
	at org.jetbrains.kotlin.cli.common.CLICompiler.execImpl(CLICompiler.kt:49)
	at org.jetbrains.kotlin.cli.common.CLITool.exec(CLITool.kt:101)
	at org.jetbrains.kotlin.incremental.IncrementalJvmCompilerRunner.runCompiler(IncrementalJvmCompilerRunner.kt:464)
	at org.jetbrains.kotlin.incremental.IncrementalJvmCompilerRunner.runCompiler(IncrementalJvmCompilerRunner.kt:73)
	at org.jetbrains.kotlin.incremental.IncrementalCompilerRunner.doCompile(IncrementalCompilerRunner.kt:506)
	at org.jetbrains.kotlin.incremental.IncrementalCompilerRunner.compileImpl(IncrementalCompilerRunner.kt:423)
	at org.jetbrains.kotlin.incremental.IncrementalCompilerRunner.compileNonIncrementally(IncrementalCompilerRunner.kt:301)
	at org.jetbrains.kotlin.incremental.IncrementalCompilerRunner.compile(IncrementalCompilerRunner.kt:129)
	at org.jetbrains.kotlin.daemon.CompileServiceImplBase.execIncrementalCompiler(CompileServiceImpl.kt:675)
	at org.jetbrains.kotlin.daemon.CompileServiceImplBase.access$execIncrementalCompiler(CompileServiceImpl.kt:92)
	at org.jetbrains.kotlin.daemon.CompileServiceImpl.compile(CompileServiceImpl.kt:1660)
	at jdk.internal.reflect.GeneratedMethodAccessor94.invoke(Unknown Source)
	at java.base/jdk.internal.reflect.DelegatingMethodAccessorImpl.invoke(DelegatingMethodAccessorImpl.java:43)
	at java.base/java.lang.reflect.Method.invoke(Method.java:568)
	at java.rmi/sun.rmi.server.UnicastServerRef.dispatch(UnicastServerRef.java:360)
	at java.rmi/sun.rmi.transport.Transport$1.run(Transport.java:200)
	at java.rmi/sun.rmi.transport.Transport$1.run(Transport.java:197)
	at java.base/java.security.AccessController.doPrivileged(AccessController.java:712)
	at java.rmi/sun.rmi.transport.Transport.serviceCall(Transport.java:196)
	at java.rmi/sun.rmi.transport.tcp.TCPTransport.handleMessages(TCPTransport.java:587)
	at java.rmi/sun.rmi.transport.tcp.TCPTransport$ConnectionHandler.run0(TCPTransport.java:828)
	at java.rmi/sun.rmi.transport.tcp.TCPTransport$ConnectionHandler.lambda$run$0(TCPTransport.java:705)
	at java.base/java.security.AccessController.doPrivileged(AccessController.java:399)
	at java.rmi/sun.rmi.transport.tcp.TCPTransport$ConnectionHandler.run(TCPTransport.java:704)
	at java.base/java.util.concurrent.ThreadPoolExecutor.runWorker(ThreadPoolExecutor.java:1136)
	at java.base/java.util.concurrent.ThreadPoolExecutor$Worker.run(ThreadPoolExecutor.java:635)
	at java.base/java.lang.Thread.run(Thread.java:833)
Caused by: java.lang.OutOfMemoryError: GC overhead limit exceeded
	at org.jetbrains.org.objectweb.asm.tree.analysis.Frame.<init>(Frame.java:78)
	at org.jetbrains.kotlin.codegen.optimization.fixStack.FixStackAnalyzer$FixStackFrame.<init>(FixStackAnalyzer.kt:98)
	at org.jetbrains.kotlin.codegen.optimization.fixStack.FixStackAnalyzer.analyzer$lambda$0(FixStackAnalyzer.kt:46)
	at org.jetbrains.kotlin.codegen.optimization.fixStack.FixStackAnalyzer$$Lambda$2291/0x0000000801790df0.invoke(Unknown Source)
	at org.jetbrains.kotlin.codegen.optimization.common.FastAnalyzer.fastMergeControlFlowEdge(FastAnalyzer.kt:256)
	at org.jetbrains.kotlin.codegen.optimization.common.FastAnalyzer.mergeControlFlowEdge(FastAnalyzer.kt:214)
	at org.jetbrains.kotlin.codegen.optimization.common.FastAnalyzer.processControlFlowEdge(FastAnalyzer.kt:208)
	at org.jetbrains.kotlin.codegen.optimization.common.FastAnalyzer.processControlFlowEdge$default(FastAnalyzer.kt:206)
	at org.jetbrains.kotlin.codegen.optimization.common.FastAnalyzer.visitOpInsn(FastAnalyzer.kt:292)
	at org.jetbrains.kotlin.codegen.optimization.common.FastAnalyzer.visitMeaningfulInstruction(FastAnalyzer.kt:281)
	at org.jetbrains.kotlin.codegen.optimization.common.FastAnalyzer.analyzeInstruction(FastAnalyzer.kt:113)
	at org.jetbrains.kotlin.codegen.optimization.common.FastAnalyzer.analyzeMainLoop(FastAnalyzer.kt:74)
	at org.jetbrains.kotlin.codegen.optimization.common.FastAnalyzer.analyze(FastAnalyzer.kt:53)
	at org.jetbrains.kotlin.codegen.optimization.fixStack.FixStackAnalyzer.analyze(FixStackAnalyzer.kt:60)
	at org.jetbrains.kotlin.codegen.optimization.fixStack.FixStackMethodTransformer.analyzeAndTransformBreakContinueGotos(FixStackMethodTransformer.kt:55)
	at org.jetbrains.kotlin.codegen.optimization.fixStack.FixStackMethodTransformer.transform(FixStackMethodTransformer.kt:44)
	at org.jetbrains.kotlin.codegen.optimization.transformer.CompositeMethodTransformer.transform(CompositeMethodTransformer.kt:25)
	at org.jetbrains.kotlin.codegen.optimization.transformer.CompositeMethodTransformer.transform(CompositeMethodTransformer.kt:25)
	at org.jetbrains.kotlin.codegen.optimization.OptimizationMethodVisitor.performTransformations(OptimizationMethodVisitor.kt:70)
	at org.jetbrains.kotlin.codegen.TransformationMethodVisitor.visitEnd(TransformationMethodVisitor.kt:67)
	at org.jetbrains.org.objectweb.asm.MethodVisitor.visitEnd(MethodVisitor.java:783)
	at org.jetbrains.org.objectweb.asm.tree.MethodNode.accept(MethodNode.java:772)
	at org.jetbrains.kotlin.backend.jvm.codegen.ClassCodegen.generateMethod(ClassCodegen.kt:453)
	at org.jetbrains.kotlin.backend.jvm.codegen.ClassCodegen.generate(ClassCodegen.kt:168)
	at org.jetbrains.kotlin.backend.jvm.FileCodegen.lower(JvmPhases.kt:39)
	at org.jetbrains.kotlin.backend.common.phaser.PhaseFactoriesKt.createFilePhase$lambda$4(PhaseFactories.kt:71)
	at org.jetbrains.kotlin.backend.common.phaser.PhaseFactoriesKt$$Lambda$168/0x0000000800d22fc0.invoke(Unknown Source)
	at org.jetbrains.kotlin.backend.common.phaser.PhaseBuildersKt$createSimpleNamedCompilerPhase$1.phaseBody(PhaseBuilders.kt:69)
	at org.jetbrains.kotlin.backend.common.phaser.SimpleNamedCompilerPhase.phaseBody(CompilerPhase.kt:226)
	at org.jetbrains.kotlin.backend.common.phaser.AbstractNamedCompilerPhase.invoke(CompilerPhase.kt:113)
	at org.jetbrains.kotlin.backend.common.phaser.PerformByIrFilePhase.invokeSequential(performByIrFile.kt:62)
	at org.jetbrains.kotlin.backend.common.phaser.PerformByIrFilePhase.invoke(performByIrFile.kt:52)


